[
  {
    "status": "ready",
    "indicatorId": "econ.world.cmp.gdp_total.in",
    "observations": 65,
    "artifact": "data/series/worldbank.in.econ.world.cmp.gdp_total.in.json",
    "fetchedAt": "2026-06-05T08:32:27.960Z",
    "latest": {
      "date": "2024",
      "value": 3909891533858.08
    }
  },
  {
    "status": "ready",
    "indicatorId": "econ.world.cmp.gdp_total.chn",
    "observations": 65,
    "artifact": "data/series/worldbank.chn.econ.world.cmp.gdp_total.chn.json",
    "fetchedAt": "2026-06-05T08:32:27.960Z",
    "latest": {
      "date": "2024",
      "value": 18743803170827.2
    }
  },
  {
    "status": "ready",
    "indicatorId": "econ.world.cmp.gdp_total.kor",
    "observations": 65,
    "artifact": "data/series/worldbank.kor.econ.world.cmp.gdp_total.kor.json",
    "fetchedAt": "2026-06-05T08:32:27.960Z",
    "latest": {
      "date": "2024",
      "value": 1875388209406.8
    }
  },
  {
    "status": "ready",
    "indicatorId": "econ.world.cmp.gdp_total.bgd",
    "observations": 65,
    "artifact": "data/series/worldbank.bgd.econ.world.cmp.gdp_total.bgd.json",
    "fetchedAt": "2026-06-05T08:32:27.960Z",
    "latest": {
      "date": "2024",
      "value": 450119432068.852
    }
  },
  {
    "status": "ready",
    "indicatorId": "econ.world.cmp.gdp_total.idn",
    "observations": 58,
    "artifact": "data/series/worldbank.idn.econ.world.cmp.gdp_total.idn.json",
    "fetchedAt": "2026-06-05T08:32:27.960Z",
    "latest": {
      "date": "2024",
      "value": 1396300098190.97
    }
  },
  {
    "status": "ready",
    "indicatorId": "econ.world.cmp.gdp_total.vnm",
    "observations": 40,
    "artifact": "data/series/worldbank.vnm.econ.world.cmp.gdp_total.vnm.json",
    "fetchedAt": "2026-06-05T08:32:27.960Z",
    "latest": {
      "date": "2024",
      "value": 476388230307.175
    }
  },
  {
    "status": "ready",
    "indicatorId": "econ.world.cmp.gdp_total.jpn",
    "observations": 65,
    "artifact": "data/series/worldbank.jpn.econ.world.cmp.gdp_total.jpn.json",
    "fetchedAt": "2026-06-05T08:32:27.960Z",
    "latest": {
      "date": "2024",
      "value": 4027597523550.58
    }
  },
  {
    "status": "ready",
    "indicatorId": "econ.world.cmp.gdp_total.deu",
    "observations": 65,
    "artifact": "data/series/worldbank.deu.econ.world.cmp.gdp_total.deu.json",
    "fetchedAt": "2026-06-05T08:32:27.960Z",
    "latest": {
      "date": "2024",
      "value": 4685592577804.69
    }
  },
  {
    "status": "ready",
    "indicatorId": "econ.world.cmp.gdp_total.usa",
    "observations": 65,
    "artifact": "data/series/worldbank.usa.econ.world.cmp.gdp_total.usa.json",
    "fetchedAt": "2026-06-05T08:32:27.960Z",
    "latest": {
      "date": "2024",
      "value": 28750956130731.2
    }
  },
  {
    "status": "ready",
    "indicatorId": "econ.world.cmp.gdp_total.gbr",
    "observations": 65,
    "artifact": "data/series/worldbank.gbr.econ.world.cmp.gdp_total.gbr.json",
    "fetchedAt": "2026-06-05T08:32:27.960Z",
    "latest": {
      "date": "2024",
      "value": 3686033044482.13
    }
  },
  {
    "status": "ready",
    "indicatorId": "econ.world.cmp.gdp_pc.in",
    "observations": 65,
    "artifact": "data/series/worldbank.in.econ.world.cmp.gdp_pc.in.json",
    "fetchedAt": "2026-06-05T08:32:27.960Z",
    "latest": {
      "date": "2024",
      "value": 2694.73780859961
    }
  },
  {
    "status": "ready",
    "indicatorId": "econ.world.cmp.gdp_pc.chn",
    "observations": 65,
    "artifact": "data/series/worldbank.chn.econ.world.cmp.gdp_pc.chn.json",
    "fetchedAt": "2026-06-05T08:32:27.960Z",
    "latest": {
      "date": "2024",
      "value": 13303.1481543868
    }
  },
  {
    "status": "ready",
    "indicatorId": "econ.world.cmp.gdp_pc.kor",
    "observations": 65,
    "artifact": "data/series/worldbank.kor.econ.world.cmp.gdp_pc.kor.json",
    "fetchedAt": "2026-06-05T08:32:27.960Z",
    "latest": {
      "date": "2024",
      "value": 36238.639908315
    }
  },
  {
    "status": "ready",
    "indicatorId": "econ.world.cmp.gdp_pc.bgd",
    "observations": 65,
    "artifact": "data/series/worldbank.bgd.econ.world.cmp.gdp_pc.bgd.json",
    "fetchedAt": "2026-06-05T08:32:27.960Z",
    "latest": {
      "date": "2024",
      "value": 2593.41611680774
    }
  },
  {
    "status": "ready",
    "indicatorId": "econ.world.cmp.gdp_pc.idn",
    "observations": 58,
    "artifact": "data/series/worldbank.idn.econ.world.cmp.gdp_pc.idn.json",
    "fetchedAt": "2026-06-05T08:32:27.960Z",
    "latest": {
      "date": "2024",
      "value": 4925.43048751861
    }
  },
  {
    "status": "ready",
    "indicatorId": "econ.world.cmp.gdp_pc.vnm",
    "observations": 40,
    "artifact": "data/series/worldbank.vnm.econ.world.cmp.gdp_pc.vnm.json",
    "fetchedAt": "2026-06-05T08:32:27.960Z",
    "latest": {
      "date": "2024",
      "value": 4717.29028732449
    }
  },
  {
    "status": "ready",
    "indicatorId": "econ.world.cmp.gdp_pc.jpn",
    "observations": 65,
    "artifact": "data/series/worldbank.jpn.econ.world.cmp.gdp_pc.jpn.json",
    "fetchedAt": "2026-06-05T08:32:27.960Z",
    "latest": {
      "date": "2024",
      "value": 32487.0778047567
    }
  },
  {
    "status": "ready",
    "indicatorId": "econ.world.cmp.gdp_pc.deu",
    "observations": 65,
    "artifact": "data/series/worldbank.deu.econ.world.cmp.gdp_pc.deu.json",
    "fetchedAt": "2026-06-05T08:32:27.960Z",
    "latest": {
      "date": "2024",
      "value": 56103.7323182554
    }
  },
  {
    "status": "ready",
    "indicatorId": "econ.world.cmp.gdp_pc.usa",
    "observations": 65,
    "artifact": "data/series/worldbank.usa.econ.world.cmp.gdp_pc.usa.json",
    "fetchedAt": "2026-06-05T08:32:27.960Z",
    "latest": {
      "date": "2024",
      "value": 84534.0407841548
    }
  },
  {
    "status": "ready",
    "indicatorId": "econ.world.cmp.gdp_pc.gbr",
    "observations": 65,
    "artifact": "data/series/worldbank.gbr.econ.world.cmp.gdp_pc.gbr.json",
    "fetchedAt": "2026-06-05T08:32:27.960Z",
    "latest": {
      "date": "2024",
      "value": 53246.3676145108
    }
  }
]
