{
  "schemaVersion": 1,
  "questionId": "q.health.life",
  "question": "How long do Indians live?",
  "priority": "core",
  "requiredIndicatorIds": [
    "health.life_expectancy",
    "health.who.life_expectancy"
  ],
  "availableIndicatorIds": [
    "health.who.life_expectancy",
    "health.life_expectancy"
  ],
  "lockedNumbers": [
    {
      "label": "Life expectancy at birth: TimeDim",
      "value": 2021,
      "date": 2021,
      "unit": "years",
      "sourceId": "who-gho",
      "indicatorId": "health.who.life_expectancy"
    },
    {
      "label": "Life expectancy at birth: NumericValue",
      "value": 67.30780612,
      "date": 2021,
      "unit": "years",
      "sourceId": "who-gho",
      "indicatorId": "health.who.life_expectancy"
    },
    {
      "label": "Life expectancy at birth: Low",
      "value": 66.88529954,
      "date": 2021,
      "unit": "years",
      "sourceId": "who-gho",
      "indicatorId": "health.who.life_expectancy"
    },
    {
      "label": "Life expectancy at birth: High",
      "value": 67.84495417,
      "date": 2021,
      "unit": "years",
      "sourceId": "who-gho",
      "indicatorId": "health.who.life_expectancy"
    },
    {
      "label": "Life expectancy at birth: TimeDimensionValue",
      "value": 2021,
      "date": 2021,
      "unit": "years",
      "sourceId": "who-gho",
      "indicatorId": "health.who.life_expectancy"
    },
    {
      "label": "Life expectancy at birth: TimeDim",
      "value": 2021,
      "date": 2021,
      "unit": "years",
      "sourceId": "who-gho",
      "indicatorId": "health.who.life_expectancy"
    },
    {
      "label": "Life expectancy at birth: NumericValue",
      "value": 65.77192893,
      "date": 2021,
      "unit": "years",
      "sourceId": "who-gho",
      "indicatorId": "health.who.life_expectancy"
    },
    {
      "label": "Life expectancy at birth: Low",
      "value": 65.33751813,
      "date": 2021,
      "unit": "years",
      "sourceId": "who-gho",
      "indicatorId": "health.who.life_expectancy"
    },
    {
      "label": "Life expectancy at birth: High",
      "value": 66.35016097,
      "date": 2021,
      "unit": "years",
      "sourceId": "who-gho",
      "indicatorId": "health.who.life_expectancy"
    },
    {
      "label": "Life expectancy at birth: TimeDimensionValue",
      "value": 2021,
      "date": 2021,
      "unit": "years",
      "sourceId": "who-gho",
      "indicatorId": "health.who.life_expectancy"
    },
    {
      "label": "Life expectancy at birth: TimeDim",
      "value": 2021,
      "date": 2021,
      "unit": "years",
      "sourceId": "who-gho",
      "indicatorId": "health.who.life_expectancy"
    },
    {
      "label": "Life expectancy at birth: NumericValue",
      "value": 69.01961502,
      "date": 2021,
      "unit": "years",
      "sourceId": "who-gho",
      "indicatorId": "health.who.life_expectancy"
    },
    {
      "label": "Life expectancy at birth, latest",
      "value": 72.235,
      "date": "2024",
      "unit": "years",
      "sourceId": "worldbank",
      "indicatorId": "health.life_expectancy"
    },
    {
      "label": "Life expectancy at birth, earliest",
      "value": 45.61,
      "date": "1960",
      "unit": "years",
      "sourceId": "worldbank",
      "indicatorId": "health.life_expectancy"
    }
  ],
  "sourceSummaries": [
    {
      "indicatorId": "health.who.life_expectancy",
      "title": "Life expectancy at birth",
      "sourceId": "who-gho",
      "sourceIndicatorId": "WHOSIS_000001",
      "unit": "years",
      "geography": {
        "type": "country",
        "id": "IND",
        "name": "India"
      },
      "rows": 66,
      "dimensions": [
        "Id",
        "IndicatorCode",
        "SpatialDimType",
        "SpatialDim",
        "ParentLocationCode",
        "TimeDimType",
        "ParentLocation",
        "Dim1Type",
        "Dim1",
        "TimeDim",
        "Dim2Type",
        "Dim2",
        "Dim3Type",
        "Dim3",
        "DataSourceDimType",
        "DataSourceDim",
        "Value",
        "NumericValue",
        "Low",
        "High",
        "Comments",
        "Date",
        "TimeDimensionValue",
        "TimeDimensionBegin",
        "TimeDimensionEnd"
      ],
      "latestRows": [
        {
          "Id": 7882519,
          "IndicatorCode": "WHOSIS_000001",
          "SpatialDimType": "COUNTRY",
          "SpatialDim": "IND",
          "ParentLocationCode": "SEAR",
          "TimeDimType": "YEAR",
          "ParentLocation": "South-East Asia",
          "Dim1Type": "SEX",
          "Dim1": "SEX_BTSX",
          "TimeDim": 2021,
          "Dim2Type": null,
          "Dim2": null,
          "Dim3Type": null,
          "Dim3": null,
          "DataSourceDimType": null,
          "DataSourceDim": null,
          "Value": "67.3 [66.9-67.8]",
          "NumericValue": 67.30780612,
          "Low": 66.88529954,
          "High": 67.84495417,
          "Comments": null,
          "Date": "2024-08-02T09:43:39.193+02:00",
          "TimeDimensionValue": "2021",
          "TimeDimensionBegin": "2021-01-01T00:00:00+01:00",
          "TimeDimensionEnd": "2021-12-31T00:00:00+01:00"
        },
        {
          "Id": 8921165,
          "IndicatorCode": "WHOSIS_000001",
          "SpatialDimType": "COUNTRY",
          "SpatialDim": "IND",
          "ParentLocationCode": "SEAR",
          "TimeDimType": "YEAR",
          "ParentLocation": "South-East Asia",
          "Dim1Type": "SEX",
          "Dim1": "SEX_MLE",
          "TimeDim": 2021,
          "Dim2Type": null,
          "Dim2": null,
          "Dim3Type": null,
          "Dim3": null,
          "DataSourceDimType": null,
          "DataSourceDim": null,
          "Value": "65.8 [65.3-66.4]",
          "NumericValue": 65.77192893,
          "Low": 65.33751813,
          "High": 66.35016097,
          "Comments": null,
          "Date": "2024-08-02T09:43:39.193+02:00",
          "TimeDimensionValue": "2021",
          "TimeDimensionBegin": "2021-01-01T00:00:00+01:00",
          "TimeDimensionEnd": "2021-12-31T00:00:00+01:00"
        },
        {
          "Id": 9427571,
          "IndicatorCode": "WHOSIS_000001",
          "SpatialDimType": "COUNTRY",
          "SpatialDim": "IND",
          "ParentLocationCode": "SEAR",
          "TimeDimType": "YEAR",
          "ParentLocation": "South-East Asia",
          "Dim1Type": "SEX",
          "Dim1": "SEX_FMLE",
          "TimeDim": 2021,
          "Dim2Type": null,
          "Dim2": null,
          "Dim3Type": null,
          "Dim3": null,
          "DataSourceDimType": null,
          "DataSourceDim": null,
          "Value": "69.0 [68.6-69.5]",
          "NumericValue": 69.01961502,
          "Low": 68.57177841,
          "High": 69.52854319,
          "Comments": null,
          "Date": "2024-08-02T09:43:39.193+02:00",
          "TimeDimensionValue": "2021",
          "TimeDimensionBegin": "2021-01-01T00:00:00+01:00",
          "TimeDimensionEnd": "2021-12-31T00:00:00+01:00"
        },
        {
          "Id": 418826,
          "IndicatorCode": "WHOSIS_000001",
          "SpatialDimType": "COUNTRY",
          "SpatialDim": "IND",
          "ParentLocationCode": "SEAR",
          "TimeDimType": "YEAR",
          "ParentLocation": "South-East Asia",
          "Dim1Type": "SEX",
          "Dim1": "SEX_BTSX",
          "TimeDim": 2020,
          "Dim2Type": null,
          "Dim2": null,
          "Dim3Type": null,
          "Dim3": null,
          "DataSourceDimType": null,
          "DataSourceDim": null,
          "Value": "70.2 [69.7-70.6]",
          "NumericValue": 70.1869093,
          "Low": 69.70785272,
          "High": 70.64393376,
          "Comments": null,
          "Date": "2024-08-02T09:43:39.193+02:00",
          "TimeDimensionValue": "2020",
          "TimeDimensionBegin": "2020-01-01T00:00:00+01:00",
          "TimeDimensionEnd": "2020-12-31T00:00:00+01:00"
        },
        {
          "Id": 8474090,
          "IndicatorCode": "WHOSIS_000001",
          "SpatialDimType": "COUNTRY",
          "SpatialDim": "IND",
          "ParentLocationCode": "SEAR",
          "TimeDimType": "YEAR",
          "ParentLocation": "South-East Asia",
          "Dim1Type": "SEX",
          "Dim1": "SEX_FMLE",
          "TimeDim": 2020,
          "Dim2Type": null,
          "Dim2": null,
          "Dim3Type": null,
          "Dim3": null,
          "DataSourceDimType": null,
          "DataSourceDim": null,
          "Value": "72.2 [71.7-72.7]",
          "NumericValue": 72.17767618,
          "Low": 71.66452185,
          "High": 72.65302799,
          "Comments": null,
          "Date": "2024-08-02T09:43:39.193+02:00",
          "TimeDimensionValue": "2020",
          "TimeDimensionBegin": "2020-01-01T00:00:00+01:00",
          "TimeDimensionEnd": "2020-12-31T00:00:00+01:00"
        },
        {
          "Id": 10044344,
          "IndicatorCode": "WHOSIS_000001",
          "SpatialDimType": "COUNTRY",
          "SpatialDim": "IND",
          "ParentLocationCode": "SEAR",
          "TimeDimType": "YEAR",
          "ParentLocation": "South-East Asia",
          "Dim1Type": "SEX",
          "Dim1": "SEX_MLE",
          "TimeDim": 2020,
          "Dim2Type": null,
          "Dim2": null,
          "Dim3Type": null,
          "Dim3": null,
          "DataSourceDimType": null,
          "DataSourceDim": null,
          "Value": "68.4 [67.9-68.9]",
          "NumericValue": 68.40590232,
          "Low": 67.94149595,
          "High": 68.92197983,
          "Comments": null,
          "Date": "2024-08-02T09:43:39.193+02:00",
          "TimeDimensionValue": "2020",
          "TimeDimensionBegin": "2020-01-01T00:00:00+01:00",
          "TimeDimensionEnd": "2020-12-31T00:00:00+01:00"
        },
        {
          "Id": 1309257,
          "IndicatorCode": "WHOSIS_000001",
          "SpatialDimType": "COUNTRY",
          "SpatialDim": "IND",
          "ParentLocationCode": "SEAR",
          "TimeDimType": "YEAR",
          "ParentLocation": "South-East Asia",
          "Dim1Type": "SEX",
          "Dim1": "SEX_FMLE",
          "TimeDim": 2019,
          "Dim2Type": null,
          "Dim2": null,
          "Dim3Type": null,
          "Dim3": null,
          "DataSourceDimType": null,
          "DataSourceDim": null,
          "Value": "72.4 [72.0-72.9]",
          "NumericValue": 72.41190387,
          "Low": 72.02726151,
          "High": 72.91110217,
          "Comments": null,
          "Date": "2024-08-02T09:43:39.193+02:00",
          "TimeDimensionValue": "2019",
          "TimeDimensionBegin": "2019-01-01T00:00:00+01:00",
          "TimeDimensionEnd": "2019-12-31T00:00:00+01:00"
        },
        {
          "Id": 3403733,
          "IndicatorCode": "WHOSIS_000001",
          "SpatialDimType": "COUNTRY",
          "SpatialDim": "IND",
          "ParentLocationCode": "SEAR",
          "TimeDimType": "YEAR",
          "ParentLocation": "South-East Asia",
          "Dim1Type": "SEX",
          "Dim1": "SEX_MLE",
          "TimeDim": 2019,
          "Dim2Type": null,
          "Dim2": null,
          "Dim3Type": null,
          "Dim3": null,
          "DataSourceDimType": null,
          "DataSourceDim": null,
          "Value": "69.2 [68.7-69.8]",
          "NumericValue": 69.17521966,
          "Low": 68.73542462,
          "High": 69.75869336,
          "Comments": null,
          "Date": "2024-08-02T09:43:39.193+02:00",
          "TimeDimensionValue": "2019",
          "TimeDimensionBegin": "2019-01-01T00:00:00+01:00",
          "TimeDimensionEnd": "2019-12-31T00:00:00+01:00"
        },
        {
          "Id": 4525133,
          "IndicatorCode": "WHOSIS_000001",
          "SpatialDimType": "COUNTRY",
          "SpatialDim": "IND",
          "ParentLocationCode": "SEAR",
          "TimeDimType": "YEAR",
          "ParentLocation": "South-East Asia",
          "Dim1Type": "SEX",
          "Dim1": "SEX_BTSX",
          "TimeDim": 2019,
          "Dim2Type": null,
          "Dim2": null,
          "Dim3Type": null,
          "Dim3": null,
          "DataSourceDimType": null,
          "DataSourceDim": null,
          "Value": "70.7 [70.3-71.3]",
          "NumericValue": 70.72711152,
          "Low": 70.2876005,
          "High": 71.27232171,
          "Comments": null,
          "Date": "2024-08-02T09:43:39.193+02:00",
          "TimeDimensionValue": "2019",
          "TimeDimensionBegin": "2019-01-01T00:00:00+01:00",
          "TimeDimensionEnd": "2019-12-31T00:00:00+01:00"
        },
        {
          "Id": 2482373,
          "IndicatorCode": "WHOSIS_000001",
          "SpatialDimType": "COUNTRY",
          "SpatialDim": "IND",
          "ParentLocationCode": "SEAR",
          "TimeDimType": "YEAR",
          "ParentLocation": "South-East Asia",
          "Dim1Type": "SEX",
          "Dim1": "SEX_BTSX",
          "TimeDim": 2018,
          "Dim2Type": null,
          "Dim2": null,
          "Dim3Type": null,
          "Dim3": null,
          "DataSourceDimType": null,
          "DataSourceDim": null,
          "Value": "70.4 [69.9-70.9]",
          "NumericValue": 70.35439242,
          "Low": 69.88836402,
          "High": 70.85554138,
          "Comments": null,
          "Date": "2024-08-02T09:43:39.193+02:00",
          "TimeDimensionValue": "2018",
          "TimeDimensionBegin": "2018-01-01T00:00:00+01:00",
          "TimeDimensionEnd": "2018-12-31T00:00:00+01:00"
        }
      ]
    },
    {
      "indicatorId": "health.life_expectancy",
      "title": "Life expectancy at birth",
      "sourceId": "worldbank",
      "sourceIndicatorId": "SP.DYN.LE00.IN",
      "unit": "years",
      "frequency": "annual",
      "geography": {
        "type": "country",
        "id": "IN",
        "name": "India"
      },
      "observations": 66,
      "earliest": {
        "date": "1960",
        "value": 45.61
      },
      "latest": {
        "date": "2024",
        "value": 72.235
      }
    }
  ],
  "caveats": [
    "Use only figures present in lockedNumbers or sourceSummaries.",
    "If source coverage is thin, say so directly.",
    "Do not compare states, districts, or cities unless the evidence packet contains those geographies."
  ],
  "forbiddenClaims": [
    "Do not invent current-year figures.",
    "Do not infer causality from a trend unless the evidence explicitly supports it.",
    "Do not cite a source that is not present in sourceSummaries."
  ]
}
