{
  "schemaVersion": 1,
  "artifactType": "series",
  "indicatorId": "prices.cpi.ex_food.index",
  "title": "CPI excluding food (index)",
  "sourceId": "indiadatahub",
  "sourceIndicatorId": "MOINCPAXFD12M",
  "sourceUrl": "https://feeds.indiadatahub.com/documentation?urls.primaryName=Economic%20Monitor",
  "unit": "index (2012=100)",
  "frequency": "monthly",
  "geography": {
    "type": "country",
    "id": "IND",
    "name": "India"
  },
  "dimensions": [],
  "fetchedAt": "2026-06-03T01:04:10.546Z",
  "observations": [
    {
      "date": "2011-01",
      "value": 87.1235685260436
    },
    {
      "date": "2011-02",
      "value": 87.7221832286664
    },
    {
      "date": "2011-03",
      "value": 88.3074251939416
    },
    {
      "date": "2011-04",
      "value": 89.1966937569265
    },
    {
      "date": "2011-05",
      "value": 90.0401736239379
    },
    {
      "date": "2011-06",
      "value": 90.7083671961581
    },
    {
      "date": "2011-07",
      "value": 91.7422423346878
    },
    {
      "date": "2011-08",
      "value": 92.5498891762098
    },
    {
      "date": "2011-09",
      "value": 93.4493165866272
    },
    {
      "date": "2011-10",
      "value": 94.2943110454378
    },
    {
      "date": "2011-11",
      "value": 95.1776320650166
    },
    {
      "date": "2011-12",
      "value": 95.6476172885113
    },
    {
      "date": "2012-01",
      "value": 96.3024011821204
    },
    {
      "date": "2012-02",
      "value": 96.7464721093461
    },
    {
      "date": "2012-03",
      "value": 97.2488178795715
    },
    {
      "date": "2012-04",
      "value": 98.0538973032878
    },
    {
      "date": "2012-05",
      "value": 98.8370705578131
    },
    {
      "date": "2012-06",
      "value": 99.7039157739194
    },
    {
      "date": "2012-07",
      "value": 100.143738455855
    },
    {
      "date": "2012-08",
      "value": 100.988732914666
    },
    {
      "date": "2012-09",
      "value": 101.91939416328
    },
    {
      "date": "2012-10",
      "value": 102.740265977096
    },
    {
      "date": "2012-11",
      "value": 103.556169190986
    },
    {
      "date": "2012-12",
      "value": 104.185814554858
    },
    {
      "date": "2013-01",
      "value": 104.822903583303
    },
    {
      "date": "2013-02",
      "value": 105.283561137791
    },
    {
      "date": "2013-03",
      "value": 105.552992242335
    },
    {
      "date": "2013-04",
      "value": 105.786368673809
    },
    {
      "date": "2013-05",
      "value": 106.095197635759
    },
    {
      "date": "2013-06",
      "value": 106.849445881049
    },
    {
      "date": "2013-07",
      "value": 107.86274473587
    },
    {
      "date": "2013-08",
      "value": 108.796195049871
    },
    {
      "date": "2013-09",
      "value": 109.801366826745
    },
    {
      "date": "2013-10",
      "value": 110.235851496121
    },
    {
      "date": "2013-11",
      "value": 110.844421869228
    },
    {
      "date": "2013-12",
      "value": 111.125027705948
    },
    {
      "date": "2014-01",
      "value": 111.738529737717
    },
    {
      "date": "2014-02",
      "value": 112.157222016993
    },
    {
      "date": "2014-03",
      "value": 112.591577391947
    },
    {
      "date": "2014-04",
      "value": 112.933930550425
    },
    {
      "date": "2014-05",
      "value": 113.272792759512
    },
    {
      "date": "2014-06",
      "value": 113.676763945327
    },
    {
      "date": "2014-07",
      "value": 114.596139637976
    },
    {
      "date": "2014-08",
      "value": 115.056871074991
    },
    {
      "date": "2014-09",
      "value": 115.306243073513
    },
    {
      "date": "2014-10",
      "value": 115.694735869967
    },
    {
      "date": "2014-11",
      "value": 115.934226080532
    },
    {
      "date": "2014-12",
      "value": 115.935703731068
    },
    {
      "date": "2015-01",
      "value": 116.394458810491
    },
    {
      "date": "2015-02",
      "value": 116.896416697451
    },
    {
      "date": "2015-03",
      "value": 117.453694126339
    },
    {
      "date": "2015-04",
      "value": 117.921666050979
    },
    {
      "date": "2015-05",
      "value": 118.698651643886
    },
    {
      "date": "2015-06",
      "value": 119.311396379756
    },
    {
      "date": "2015-07",
      "value": 119.722312523088
    },
    {
      "date": "2015-08",
      "value": 120.066956039897
    },
    {
      "date": "2015-09",
      "value": 120.436350203177
    },
    {
      "date": "2015-10",
      "value": 120.939268562985
    },
    {
      "date": "2015-11",
      "value": 121.382803841891
    },
    {
      "date": "2015-12",
      "value": 121.532766900628
    },
    {
      "date": "2016-01",
      "value": 122.002899889176
    },
    {
      "date": "2016-02",
      "value": 122.668489102327
    },
    {
      "date": "2016-03",
      "value": 122.840229035833
    },
    {
      "date": "2016-04",
      "value": 123.410639083857
    },
    {
      "date": "2016-05",
      "value": 123.97635759143
    },
    {
      "date": "2016-06",
      "value": 124.493960103436
    },
    {
      "date": "2016-07",
      "value": 124.994033985962
    },
    {
      "date": "2016-08",
      "value": 125.391189508681
    },
    {
      "date": "2016-09",
      "value": 126.03965644625
    },
    {
      "date": "2016-10",
      "value": 126.647173993351
    },
    {
      "date": "2016-11",
      "value": 127.0883450314
    },
    {
      "date": "2016-12",
      "value": 127.327798300702
    },
    {
      "date": "2017-01",
      "value": 127.874104174363
    },
    {
      "date": "2017-02",
      "value": 128.452271887699
    },
    {
      "date": "2017-03",
      "value": 128.963483561138
    },
    {
      "date": "2017-04",
      "value": 129.249076468415
    },
    {
      "date": "2017-05",
      "value": 129.436848910233
    },
    {
      "date": "2017-06",
      "value": 129.384835611378
    },
    {
      "date": "2017-07",
      "value": 130.064296268932
    },
    {
      "date": "2017-08",
      "value": 131.111359438493
    },
    {
      "date": "2017-09",
      "value": 131.999316586627
    },
    {
      "date": "2017-10",
      "value": 132.684798670115
    },
    {
      "date": "2017-11",
      "value": 133.875360177318
    },
    {
      "date": "2017-12",
      "value": 134.305301071297
    },
    {
      "date": "2018-01",
      "value": 134.866808274843
    },
    {
      "date": "2018-02",
      "value": 135.353361654969
    },
    {
      "date": "2018-03",
      "value": 135.946305873661
    },
    {
      "date": "2018-04",
      "value": 136.771721462874
    },
    {
      "date": "2018-05",
      "value": 137.424916882157
    },
    {
      "date": "2018-06",
      "value": 137.785759142963
    },
    {
      "date": "2018-07",
      "value": 138.519431104544
    },
    {
      "date": "2018-08",
      "value": 139.30108976727
    },
    {
      "date": "2018-09",
      "value": 140.13202807536
    },
    {
      "date": "2018-10",
      "value": 141.2924824529
    },
    {
      "date": "2018-11",
      "value": 141.79390469154
    },
    {
      "date": "2018-12",
      "value": 141.707480605837
    },
    {
      "date": "2019-01",
      "value": 141.539250092353
    },
    {
      "date": "2019-02",
      "value": 141.831473956409
    },
    {
      "date": "2019-03",
      "value": 142.274159586258
    },
    {
      "date": "2019-04",
      "value": 142.627705947543
    },
    {
      "date": "2019-05",
      "value": 142.914850387883
    },
    {
      "date": "2019-06",
      "value": 143.154820834873
    },
    {
      "date": "2019-07",
      "value": 143.646065755449
    },
    {
      "date": "2019-08",
      "value": 144.159715552272
    },
    {
      "date": "2019-09",
      "value": 144.65206871075
    },
    {
      "date": "2019-10",
      "value": 145.197229405246
    },
    {
      "date": "2019-11",
      "value": 145.745345400813
    },
    {
      "date": "2019-12",
      "value": 146.494347986701
    },
    {
      "date": "2020-01",
      "value": 147.338326560768
    },
    {
      "date": "2020-02",
      "value": 148.014573328408
    },
    {
      "date": "2020-03",
      "value": 148.362707794607
    },
    {
      "date": "2020-04",
      "value": 149.203398596232
    },
    {
      "date": "2020-05",
      "value": 149.456353897303
    },
    {
      "date": "2020-06",
      "value": 149.923106760251
    },
    {
      "date": "2020-07",
      "value": 151.253675655707
    },
    {
      "date": "2020-08",
      "value": 152.028241595863
    },
    {
      "date": "2020-09",
      "value": 152.331732545253
    },
    {
      "date": "2020-10",
      "value": 152.913114148504
    },
    {
      "date": "2020-11",
      "value": 153.498263760621
    },
    {
      "date": "2020-12",
      "value": 154.271869227928
    },
    {
      "date": "2021-01",
      "value": 155.336904322128
    },
    {
      "date": "2021-02",
      "value": 156.287735500554
    },
    {
      "date": "2021-03",
      "value": 156.970797931289
    },
    {
      "date": "2021-04",
      "value": 157.715607683783
    },
    {
      "date": "2021-05",
      "value": 159.998485408201
    },
    {
      "date": "2021-06",
      "value": 160.250720354636
    },
    {
      "date": "2021-07",
      "value": 161.384761728851
    },
    {
      "date": "2021-08",
      "value": 162.101440709272
    },
    {
      "date": "2021-09",
      "value": 162.528223125231
    },
    {
      "date": "2021-10",
      "value": 163.679442186923
    },
    {
      "date": "2021-11",
      "value": 164.152087181382
    },
    {
      "date": "2021-12",
      "value": 164.465164388622
    },
    {
      "date": "2022-01",
      "value": 165.220687107499
    },
    {
      "date": "2022-02",
      "value": 166.173716291097
    },
    {
      "date": "2022-03",
      "value": 167.121906169191
    },
    {
      "date": "2022-04",
      "value": 169.434429257481
    },
    {
      "date": "2022-05",
      "value": 170.422700406354
    },
    {
      "date": "2022-06",
      "value": 170.647026228297
    },
    {
      "date": "2022-07",
      "value": 171.9286110084965
    },
    {
      "date": "2022-08",
      "value": 172.57922053934246
    },
    {
      "date": "2022-09",
      "value": 173.28293313631326
    },
    {
      "date": "2022-10",
      "value": 174.2942002216476
    },
    {
      "date": "2022-11",
      "value": 174.97977465829334
    },
    {
      "date": "2022-12",
      "value": 175.4605282600665
    },
    {
      "date": "2023-01",
      "value": 176.275452530477
    },
    {
      "date": "2023-02",
      "value": 177.034244551164
    },
    {
      "date": "2023-03",
      "value": 177.417177687477
    },
    {
      "date": "2023-04",
      "value": 178.299612116734
    },
    {
      "date": "2023-05",
      "value": 178.957037310676
    },
    {
      "date": "2023-06",
      "value": 179.102364240857
    },
    {
      "date": "2023-07",
      "value": 180.139527151829
    },
    {
      "date": "2023-08",
      "value": 180.731381603251
    },
    {
      "date": "2023-09",
      "value": 180.064000738825
    },
    {
      "date": "2023-10",
      "value": 180.665108976727
    },
    {
      "date": "2023-11",
      "value": 181.046712227558
    },
    {
      "date": "2023-12",
      "value": 181.160491318803
    },
    {
      "date": "2024-01",
      "value": 181.645400812708
    },
    {
      "date": "2024-02",
      "value": 182.054931658663
    },
    {
      "date": "2024-03",
      "value": 181.647469523458
    },
    {
      "date": "2024-04",
      "value": 182.397691171038
    },
    {
      "date": "2024-05",
      "value": 182.969375692649
    },
    {
      "date": "2024-06",
      "value": 183.168932397488
    },
    {
      "date": "2024-07",
      "value": 184.153287772442
    },
    {
      "date": "2024-08",
      "value": 184.833671961581
    },
    {
      "date": "2024-09",
      "value": 185.259142962689
    },
    {
      "date": "2024-10",
      "value": 186.08319172515704
    },
    {
      "date": "2024-11",
      "value": 186.39205762837088
    },
    {
      "date": "2024-12",
      "value": 186.52462135205022
    },
    {
      "date": "2025-01",
      "value": 187.13611008496488
    },
    {
      "date": "2025-02",
      "value": 188.10471001108237
    },
    {
      "date": "2025-03",
      "value": 188.50277059475437
    },
    {
      "date": "2025-04",
      "value": 189.62927595123753
    },
    {
      "date": "2025-05",
      "value": 190.41322497229407
    },
    {
      "date": "2025-06",
      "value": 190.83934244551162
    },
    {
      "date": "2025-07",
      "value": 191.42282970077576
    },
    {
      "date": "2025-08",
      "value": 192.02933136313263
    },
    {
      "date": "2025-09",
      "value": 192.6655707425194
    },
    {
      "date": "2025-10",
      "value": 193.7406908016254
    },
    {
      "date": "2025-11",
      "value": 194.02920206871076
    },
    {
      "date": "2025-12",
      "value": 194.5597894347987
    }
  ],
  "metadata": {
    "sourceCategory": "Inflation",
    "sourceSubcategory": "CPI core"
  }
}
