{
  "schemaVersion": 1,
  "artifactType": "series",
  "indicatorId": "econ.nas.income_paid_abroad_nominal",
  "title": "Net primary income paid abroad (GDP − GNI)",
  "sourceId": "mospi",
  "sourceIndicatorId": "NAS_gdp_gni_gap",
  "sourceUrl": "https://esankhyiki.mospi.gov.in/macroindicators?product=nas",
  "unit": "rupees",
  "frequency": "annual",
  "geography": {
    "type": "country",
    "id": "IN",
    "name": "India"
  },
  "dimensions": [],
  "fetchedAt": "2026-06-05T13:12:12.960Z",
  "observations": [
    {
      "date": "1951-03-31",
      "value": 410000000
    },
    {
      "date": "1952-03-31",
      "value": 350000000
    },
    {
      "date": "1953-03-31",
      "value": 250000000
    },
    {
      "date": "1954-03-31",
      "value": 190000000
    },
    {
      "date": "1955-03-31",
      "value": 290000000
    },
    {
      "date": "1956-03-31",
      "value": 100000000
    },
    {
      "date": "1957-03-31",
      "value": 170000000
    },
    {
      "date": "1958-03-31",
      "value": 200000000
    },
    {
      "date": "1959-03-31",
      "value": 350000000
    },
    {
      "date": "1960-03-31",
      "value": 570000000
    },
    {
      "date": "1961-03-31",
      "value": 720000000
    },
    {
      "date": "1962-03-31",
      "value": 980000000
    },
    {
      "date": "1963-03-31",
      "value": 1080000000
    },
    {
      "date": "1964-03-31",
      "value": 1120000000
    },
    {
      "date": "1965-03-31",
      "value": 1450000000
    },
    {
      "date": "1966-03-31",
      "value": 1640000000
    },
    {
      "date": "1967-03-31",
      "value": 2300000000
    },
    {
      "date": "1968-03-31",
      "value": 2580000000
    },
    {
      "date": "1969-03-31",
      "value": 2550000000
    },
    {
      "date": "1970-03-31",
      "value": 2710000000
    },
    {
      "date": "1971-03-31",
      "value": 2840000000
    },
    {
      "date": "1972-03-31",
      "value": 2910000000
    },
    {
      "date": "1973-03-31",
      "value": 3020000000
    },
    {
      "date": "1974-03-31",
      "value": 3250000000
    },
    {
      "date": "1975-03-31",
      "value": 2910000000
    },
    {
      "date": "1976-03-31",
      "value": 2550000000
    },
    {
      "date": "1977-03-31",
      "value": 2330000000
    },
    {
      "date": "1978-03-31",
      "value": 2330000000
    },
    {
      "date": "1979-03-31",
      "value": 1560000000
    },
    {
      "date": "1980-03-31",
      "value": -1530000000
    },
    {
      "date": "1981-03-31",
      "value": -3450000000
    },
    {
      "date": "1982-03-31",
      "value": -400000000
    },
    {
      "date": "1983-03-31",
      "value": 6340000000
    },
    {
      "date": "1984-03-31",
      "value": 9440000000
    },
    {
      "date": "1985-03-31",
      "value": 14240000000
    },
    {
      "date": "1986-03-31",
      "value": 14290000000
    },
    {
      "date": "1987-03-31",
      "value": 18050000000
    },
    {
      "date": "1988-03-31",
      "value": 26190000000
    },
    {
      "date": "1989-03-31",
      "value": 44960000000
    },
    {
      "date": "1990-03-31",
      "value": 57310000000
    },
    {
      "date": "1991-03-31",
      "value": 75450000000
    },
    {
      "date": "1992-03-31",
      "value": 100770000000
    },
    {
      "date": "1993-03-31",
      "value": 116450000000
    },
    {
      "date": "1994-03-31",
      "value": 120800000000
    },
    {
      "date": "1995-03-31",
      "value": 130830000000
    },
    {
      "date": "1996-03-31",
      "value": 134840000000
    },
    {
      "date": "1997-03-31",
      "value": 130820000000
    },
    {
      "date": "1998-03-31",
      "value": 132050000000
    },
    {
      "date": "1999-03-31",
      "value": 149680000000
    },
    {
      "date": "2000-03-31",
      "value": 154310000000
    },
    {
      "date": "2001-03-31",
      "value": 227330000000
    },
    {
      "date": "2002-03-31",
      "value": 200680000000
    },
    {
      "date": "2003-03-31",
      "value": 166900000000
    },
    {
      "date": "2004-03-31",
      "value": 207080000000
    },
    {
      "date": "2005-03-31",
      "value": 223750000000
    },
    {
      "date": "2006-03-31",
      "value": 261160000000
    },
    {
      "date": "2007-03-31",
      "value": 332340000000
    },
    {
      "date": "2008-03-31",
      "value": 205120000000
    },
    {
      "date": "2009-03-31",
      "value": 329230000000
    },
    {
      "date": "2010-03-31",
      "value": 380000000000.03723
    },
    {
      "date": "2011-03-31",
      "value": 818070000000
    },
    {
      "date": "2012-03-31",
      "value": 768240000000
    },
    {
      "date": "2013-03-31",
      "value": 1167630000000
    },
    {
      "date": "2014-03-31",
      "value": 1398838077784.963
    },
    {
      "date": "2015-03-31",
      "value": 1474298741188.1423
    },
    {
      "date": "2016-03-31",
      "value": 1597790695621.9673
    },
    {
      "date": "2017-03-31",
      "value": 1764000000000
    },
    {
      "date": "2018-03-31",
      "value": 1848126425484.903
    },
    {
      "date": "2019-03-31",
      "value": 2023244672012.2173
    },
    {
      "date": "2020-03-31",
      "value": 1931136922374.0325
    },
    {
      "date": "2021-03-31",
      "value": 2666873836443.685
    },
    {
      "date": "2022-03-31",
      "value": 2778084265994.3926
    },
    {
      "date": "2023-03-31",
      "value": 3703067373316.1763
    },
    {
      "date": "2024-03-31",
      "value": 4121699008006.0063
    },
    {
      "date": "2025-03-31",
      "value": 4782970320398.51
    },
    {
      "date": "2026-03-31",
      "value": 5548890949949.995
    }
  ],
  "metadata": {
    "sourceCategory": "National Accounts",
    "sourceSubcategory": "NAS",
    "baseYear": "2011-12",
    "sourceOwner": "MoSPI / National Statistical Office"
  }
}
