{
  "schemaVersion": 1,
  "artifactType": "series",
  "indicatorId": "climate.openmeteo.raipur.mean_apparent_temperature",
  "title": "Raipur annual mean feels-like temperature",
  "sourceId": "open-meteo",
  "sourceIndicatorId": "raipur.era5.mean_apparent_temperature",
  "sourceUrl": "https://open-meteo.com/en/docs/historical-weather-api",
  "unit": "°C",
  "frequency": "annual",
  "geography": {
    "type": "city",
    "id": "raipur",
    "name": "Raipur",
    "latitude": 21.2514,
    "longitude": 81.6296
  },
  "dimensions": [
    "date",
    "value"
  ],
  "fetchedAt": "2026-06-05T08:54:49.630Z",
  "observations": [
    {
      "date": "1940",
      "value": 26.786301369863022
    },
    {
      "date": "1941",
      "value": 26.767671232876715
    },
    {
      "date": "1942",
      "value": 26.949589041095876
    },
    {
      "date": "1943",
      "value": 25.98520547945204
    },
    {
      "date": "1944",
      "value": 27.381693989071024
    },
    {
      "date": "1945",
      "value": 26.43232876712327
    },
    {
      "date": "1946",
      "value": 27.135890410958904
    },
    {
      "date": "1947",
      "value": 27.581643835616422
    },
    {
      "date": "1948",
      "value": 27.778142076502753
    },
    {
      "date": "1949",
      "value": 26.778630136986298
    },
    {
      "date": "1950",
      "value": 26.612328767123262
    },
    {
      "date": "1951",
      "value": 26.833424657534234
    },
    {
      "date": "1952",
      "value": 26.341803278688534
    },
    {
      "date": "1953",
      "value": 26.08383561643836
    },
    {
      "date": "1954",
      "value": 27.569041095890412
    },
    {
      "date": "1955",
      "value": 27.358356164383565
    },
    {
      "date": "1956",
      "value": 27.127595628415303
    },
    {
      "date": "1957",
      "value": 27.673150684931528
    },
    {
      "date": "1958",
      "value": 28.273150684931505
    },
    {
      "date": "1959",
      "value": 27.71561643835616
    },
    {
      "date": "1960",
      "value": 27.593989071038276
    },
    {
      "date": "1961",
      "value": 27.084383561643833
    },
    {
      "date": "1962",
      "value": 27.293424657534274
    },
    {
      "date": "1963",
      "value": 27.571780821917816
    },
    {
      "date": "1964",
      "value": 27.569945355191223
    },
    {
      "date": "1965",
      "value": 27.497534246575363
    },
    {
      "date": "1966",
      "value": 27.838356164383573
    },
    {
      "date": "1967",
      "value": 28.25068493150683
    },
    {
      "date": "1968",
      "value": 27.70081967213114
    },
    {
      "date": "1969",
      "value": 28.565479452054785
    },
    {
      "date": "1970",
      "value": 28.14328767123289
    },
    {
      "date": "1971",
      "value": 27.0295890410959
    },
    {
      "date": "1972",
      "value": 28.224043715847003
    },
    {
      "date": "1973",
      "value": 28.561643835616447
    },
    {
      "date": "1974",
      "value": 28.07205479452054
    },
    {
      "date": "1975",
      "value": 27.86712328767127
    },
    {
      "date": "1976",
      "value": 28.322677595628413
    },
    {
      "date": "1977",
      "value": 28.497534246575324
    },
    {
      "date": "1978",
      "value": 28.244657534246553
    },
    {
      "date": "1979",
      "value": 29.0649315068493
    },
    {
      "date": "1980",
      "value": 28.66857923497266
    },
    {
      "date": "1981",
      "value": 27.882465753424665
    },
    {
      "date": "1982",
      "value": 28.54821917808218
    },
    {
      "date": "1983",
      "value": 28.03232876712329
    },
    {
      "date": "1984",
      "value": 27.695901639344253
    },
    {
      "date": "1985",
      "value": 28.006301369863007
    },
    {
      "date": "1986",
      "value": 28.101369863013705
    },
    {
      "date": "1987",
      "value": 28.368493150684927
    },
    {
      "date": "1988",
      "value": 28.55245901639345
    },
    {
      "date": "1989",
      "value": 27.856986301369865
    },
    {
      "date": "1990",
      "value": 28.021917808219165
    },
    {
      "date": "1991",
      "value": 28.401369863013723
    },
    {
      "date": "1992",
      "value": 27.917486338797787
    },
    {
      "date": "1993",
      "value": 28.219452054794512
    },
    {
      "date": "1994",
      "value": 28.03945205479453
    },
    {
      "date": "1995",
      "value": 28.368767123287697
    },
    {
      "date": "1996",
      "value": 28.716393442622962
    },
    {
      "date": "1997",
      "value": 28.325205479452055
    },
    {
      "date": "1998",
      "value": 29.134246575342445
    },
    {
      "date": "1999",
      "value": 28.387671232876748
    },
    {
      "date": "2000",
      "value": 28.184972677595624
    },
    {
      "date": "2001",
      "value": 28.535616438356175
    },
    {
      "date": "2002",
      "value": 28.72630136986301
    },
    {
      "date": "2003",
      "value": 28.719452054794527
    },
    {
      "date": "2004",
      "value": 28.342622950819653
    },
    {
      "date": "2005",
      "value": 28.56273972602743
    },
    {
      "date": "2006",
      "value": 28.902465753424643
    },
    {
      "date": "2007",
      "value": 28.62520547945207
    },
    {
      "date": "2008",
      "value": 28.372131147540994
    },
    {
      "date": "2009",
      "value": 29.371506849315068
    },
    {
      "date": "2010",
      "value": 29.670958904109572
    },
    {
      "date": "2011",
      "value": 28.2375342465753
    },
    {
      "date": "2012",
      "value": 28.459016393442617
    },
    {
      "date": "2013",
      "value": 28.542191780821906
    },
    {
      "date": "2014",
      "value": 28.739452054794533
    },
    {
      "date": "2015",
      "value": 29.519726027397283
    },
    {
      "date": "2016",
      "value": 29.729781420765008
    },
    {
      "date": "2017",
      "value": 29.544657534246564
    },
    {
      "date": "2018",
      "value": 28.849863013698656
    },
    {
      "date": "2019",
      "value": 29.589863013698597
    },
    {
      "date": "2020",
      "value": 29.28551912568306
    },
    {
      "date": "2021",
      "value": 29.39917808219179
    },
    {
      "date": "2022",
      "value": 29.548219178082224
    },
    {
      "date": "2023",
      "value": 29.542191780821902
    },
    {
      "date": "2024",
      "value": 30.279781420765
    },
    {
      "date": "2025",
      "value": 29.0950684931507
    }
  ],
  "metadata": {
    "model": "era5",
    "startDate": "1940-01-01",
    "endDate": "2026-05-29",
    "calculation": "Average of daily mean apparent ('feels-like') temperature for each calendar year. Apparent temperature combines air temperature with humidity, wind, and radiation.",
    "threshold": null,
    "leanFetch": true
  }
}
