{
  "schemaVersion": 1,
  "artifactType": "series",
  "indicatorId": "market.rbi.bse_market_cap_monthly",
  "title": "BSE market capitalisation",
  "sourceId": "rbi-dbie",
  "sourceIndicatorId": "download/dbie_FileDownloadHDFSAction:OtherMacroeconomicTimeseriesData:Monthly:MARKET CAPITALISATION - BSE",
  "sourceUrl": "https://data.rbi.org.in/DBIE/#/dbie/home",
  "unit": "₹ Crore",
  "frequency": "monthly",
  "geography": {
    "type": "country",
    "id": "IND",
    "name": "India"
  },
  "dimensions": [
    "period"
  ],
  "fetchedAt": "2026-06-02T07:01:44.649Z",
  "observations": [
    {
      "date": "1980-03",
      "value": 5421,
      "sourcePeriodType": "month",
      "sourceDate": null
    },
    {
      "date": "1983-03",
      "value": 9769,
      "sourcePeriodType": "month",
      "sourceDate": null
    },
    {
      "date": "1984-03",
      "value": 10219,
      "sourcePeriodType": "month",
      "sourceDate": null
    },
    {
      "date": "1985-03",
      "value": 20378,
      "sourcePeriodType": "month",
      "sourceDate": null
    },
    {
      "date": "1986-03",
      "value": 21636,
      "sourcePeriodType": "month",
      "sourceDate": null
    },
    {
      "date": "1987-03",
      "value": 25937,
      "sourcePeriodType": "month",
      "sourceDate": null
    },
    {
      "date": "1988-03",
      "value": 45519,
      "sourcePeriodType": "month",
      "sourceDate": null
    },
    {
      "date": "1989-03",
      "value": 54560,
      "sourcePeriodType": "month",
      "sourceDate": null
    },
    {
      "date": "1990-03",
      "value": 65206,
      "sourcePeriodType": "month",
      "sourceDate": null
    },
    {
      "date": "1991-03",
      "value": 90836,
      "sourcePeriodType": "month",
      "sourceDate": null
    },
    {
      "date": "1992-03",
      "value": 323363,
      "sourcePeriodType": "month",
      "sourceDate": null
    },
    {
      "date": "1993-03",
      "value": 188146,
      "sourcePeriodType": "month",
      "sourceDate": null
    },
    {
      "date": "1993-04",
      "value": 175093,
      "sourcePeriodType": "month",
      "sourceDate": null
    },
    {
      "date": "1993-05",
      "value": 180904,
      "sourcePeriodType": "month",
      "sourceDate": null
    },
    {
      "date": "1993-06",
      "value": 183775,
      "sourcePeriodType": "month",
      "sourceDate": null
    },
    {
      "date": "1993-07",
      "value": 192080,
      "sourcePeriodType": "month",
      "sourceDate": null
    },
    {
      "date": "1993-08",
      "value": 217291,
      "sourcePeriodType": "month",
      "sourceDate": null
    },
    {
      "date": "1993-09",
      "value": 223549,
      "sourcePeriodType": "month",
      "sourceDate": null
    },
    {
      "date": "1993-10",
      "value": 220587,
      "sourcePeriodType": "month",
      "sourceDate": null
    },
    {
      "date": "1993-11",
      "value": 266738,
      "sourcePeriodType": "month",
      "sourceDate": null
    },
    {
      "date": "1993-12",
      "value": 305000,
      "sourcePeriodType": "month",
      "sourceDate": null
    },
    {
      "date": "1994-01",
      "value": 364139,
      "sourcePeriodType": "month",
      "sourceDate": null
    },
    {
      "date": "1994-02",
      "value": 390696,
      "sourcePeriodType": "month",
      "sourceDate": null
    },
    {
      "date": "1994-03",
      "value": 368071,
      "sourcePeriodType": "month",
      "sourceDate": null
    },
    {
      "date": "1994-04",
      "value": 364868,
      "sourcePeriodType": "month",
      "sourceDate": null
    },
    {
      "date": "1994-05",
      "value": 372977,
      "sourcePeriodType": "month",
      "sourceDate": null
    },
    {
      "date": "1994-06",
      "value": 398044,
      "sourcePeriodType": "month",
      "sourceDate": null
    },
    {
      "date": "1994-07",
      "value": 408230,
      "sourcePeriodType": "month",
      "sourceDate": null
    },
    {
      "date": "1994-08",
      "value": 446884,
      "sourcePeriodType": "month",
      "sourceDate": null
    },
    {
      "date": "1994-09",
      "value": 416966,
      "sourcePeriodType": "month",
      "sourceDate": null
    },
    {
      "date": "1994-10",
      "value": 415381,
      "sourcePeriodType": "month",
      "sourceDate": null
    },
    {
      "date": "1994-11",
      "value": 401692,
      "sourcePeriodType": "month",
      "sourceDate": null
    },
    {
      "date": "1994-12",
      "value": 400000,
      "sourcePeriodType": "month",
      "sourceDate": null
    },
    {
      "date": "1995-01",
      "value": 352443,
      "sourcePeriodType": "month",
      "sourceDate": null
    },
    {
      "date": "1995-02",
      "value": 348516,
      "sourcePeriodType": "month",
      "sourceDate": null
    },
    {
      "date": "1995-03",
      "value": 435481,
      "sourcePeriodType": "month",
      "sourceDate": null
    },
    {
      "date": "1995-04",
      "value": 455315,
      "sourcePeriodType": "month",
      "sourceDate": null
    },
    {
      "date": "1995-05",
      "value": 456781,
      "sourcePeriodType": "month",
      "sourceDate": null
    },
    {
      "date": "1995-06",
      "value": 462238,
      "sourcePeriodType": "month",
      "sourceDate": null
    },
    {
      "date": "1995-07",
      "value": 465145,
      "sourcePeriodType": "month",
      "sourceDate": null
    },
    {
      "date": "1995-08",
      "value": 503630,
      "sourcePeriodType": "month",
      "sourceDate": null
    },
    {
      "date": "1995-09",
      "value": 530819,
      "sourcePeriodType": "month",
      "sourceDate": null
    },
    {
      "date": "1995-10",
      "value": 518623,
      "sourcePeriodType": "month",
      "sourceDate": null
    },
    {
      "date": "1995-11",
      "value": 435107,
      "sourcePeriodType": "month",
      "sourceDate": null
    },
    {
      "date": "1995-12",
      "value": 447297,
      "sourcePeriodType": "month",
      "sourceDate": null
    },
    {
      "date": "1996-01",
      "value": 436396,
      "sourcePeriodType": "month",
      "sourceDate": null
    },
    {
      "date": "1996-02",
      "value": 499705,
      "sourcePeriodType": "month",
      "sourceDate": null
    },
    {
      "date": "1996-03",
      "value": 526476,
      "sourcePeriodType": "month",
      "sourceDate": null
    },
    {
      "date": "1996-04",
      "value": 585919,
      "sourcePeriodType": "month",
      "sourceDate": null
    },
    {
      "date": "1996-05",
      "value": 518640,
      "sourcePeriodType": "month",
      "sourceDate": null
    },
    {
      "date": "1996-06",
      "value": 530815,
      "sourcePeriodType": "month",
      "sourceDate": null
    },
    {
      "date": "1996-07",
      "value": 501538,
      "sourcePeriodType": "month",
      "sourceDate": null
    },
    {
      "date": "1996-08",
      "value": 497113,
      "sourcePeriodType": "month",
      "sourceDate": null
    },
    {
      "date": "1996-09",
      "value": 476805,
      "sourcePeriodType": "month",
      "sourceDate": null
    },
    {
      "date": "1996-10",
      "value": 455805,
      "sourcePeriodType": "month",
      "sourceDate": null
    },
    {
      "date": "1996-11",
      "value": 416750,
      "sourcePeriodType": "month",
      "sourceDate": null
    },
    {
      "date": "1996-12",
      "value": 439231,
      "sourcePeriodType": "month",
      "sourceDate": null
    },
    {
      "date": "1997-01",
      "value": 458261,
      "sourcePeriodType": "month",
      "sourceDate": null
    },
    {
      "date": "1997-02",
      "value": 484624,
      "sourcePeriodType": "month",
      "sourceDate": null
    },
    {
      "date": "1997-03",
      "value": 463915,
      "sourcePeriodType": "month",
      "sourceDate": null
    },
    {
      "date": "1997-04",
      "value": 502082,
      "sourcePeriodType": "month",
      "sourceDate": null
    },
    {
      "date": "1997-05",
      "value": 506391,
      "sourcePeriodType": "month",
      "sourceDate": null
    },
    {
      "date": "1997-06",
      "value": 588496,
      "sourcePeriodType": "month",
      "sourceDate": null
    },
    {
      "date": "1997-07",
      "value": 595346,
      "sourcePeriodType": "month",
      "sourceDate": null
    },
    {
      "date": "1997-08",
      "value": 550883,
      "sourcePeriodType": "month",
      "sourceDate": null
    },
    {
      "date": "1997-09",
      "value": 547728,
      "sourcePeriodType": "month",
      "sourceDate": null
    },
    {
      "date": "1997-10",
      "value": 526142,
      "sourcePeriodType": "month",
      "sourceDate": null
    },
    {
      "date": "1997-11",
      "value": 493573,
      "sourcePeriodType": "month",
      "sourceDate": null
    },
    {
      "date": "1997-12",
      "value": 503716,
      "sourcePeriodType": "month",
      "sourceDate": null
    },
    {
      "date": "1998-01",
      "value": 469513,
      "sourcePeriodType": "month",
      "sourceDate": null
    },
    {
      "date": "1998-02",
      "value": 526357,
      "sourcePeriodType": "month",
      "sourceDate": null
    },
    {
      "date": "1998-03",
      "value": 560325,
      "sourcePeriodType": "month",
      "sourceDate": null
    },
    {
      "date": "1998-04",
      "value": 580238,
      "sourcePeriodType": "month",
      "sourceDate": null
    },
    {
      "date": "1998-05",
      "value": 561849,
      "sourcePeriodType": "month",
      "sourceDate": null
    },
    {
      "date": "1998-06",
      "value": 485461,
      "sourcePeriodType": "month",
      "sourceDate": null
    },
    {
      "date": "1998-07",
      "value": 483420,
      "sourcePeriodType": "month",
      "sourceDate": null
    },
    {
      "date": "1998-08",
      "value": 464887,
      "sourcePeriodType": "month",
      "sourceDate": null
    },
    {
      "date": "1998-09",
      "value": 479711,
      "sourcePeriodType": "month",
      "sourceDate": null
    },
    {
      "date": "1998-10",
      "value": 452779,
      "sourcePeriodType": "month",
      "sourceDate": null
    },
    {
      "date": "1998-11",
      "value": 446728,
      "sourcePeriodType": "month",
      "sourceDate": null
    },
    {
      "date": "1998-12",
      "value": 477010,
      "sourcePeriodType": "month",
      "sourceDate": null
    },
    {
      "date": "1999-01",
      "value": 502451,
      "sourcePeriodType": "month",
      "sourceDate": null
    },
    {
      "date": "1999-02",
      "value": 504233,
      "sourcePeriodType": "month",
      "sourceDate": null
    },
    {
      "date": "1999-03",
      "value": 545361,
      "sourcePeriodType": "month",
      "sourceDate": null
    },
    {
      "date": "1999-04",
      "value": 488229,
      "sourcePeriodType": "month",
      "sourceDate": null
    },
    {
      "date": "1999-05",
      "value": 560965,
      "sourcePeriodType": "month",
      "sourceDate": null
    },
    {
      "date": "1999-06",
      "value": 584788,
      "sourcePeriodType": "month",
      "sourceDate": null
    },
    {
      "date": "1999-07",
      "value": 648932,
      "sourcePeriodType": "month",
      "sourceDate": null
    },
    {
      "date": "1999-08",
      "value": 710956,
      "sourcePeriodType": "month",
      "sourceDate": null
    },
    {
      "date": "1999-09",
      "value": 704568,
      "sourcePeriodType": "month",
      "sourceDate": null
    },
    {
      "date": "1999-10",
      "value": 673462,
      "sourcePeriodType": "month",
      "sourceDate": null
    },
    {
      "date": "1999-11",
      "value": 709613,
      "sourcePeriodType": "month",
      "sourceDate": null
    },
    {
      "date": "1999-12",
      "value": 803353,
      "sourcePeriodType": "month",
      "sourceDate": null
    },
    {
      "date": "2000-01",
      "value": 927383,
      "sourcePeriodType": "month",
      "sourceDate": null
    },
    {
      "date": "2000-02",
      "value": 1029257,
      "sourcePeriodType": "month",
      "sourceDate": null
    },
    {
      "date": "2000-03",
      "value": 912842,
      "sourcePeriodType": "month",
      "sourceDate": null
    },
    {
      "date": "2000-04",
      "value": 755914,
      "sourcePeriodType": "month",
      "sourceDate": null
    },
    {
      "date": "2000-05",
      "value": 702777,
      "sourcePeriodType": "month",
      "sourceDate": null
    },
    {
      "date": "2000-06",
      "value": 793230,
      "sourcePeriodType": "month",
      "sourceDate": null
    },
    {
      "date": "2000-07",
      "value": 720884,
      "sourcePeriodType": "month",
      "sourceDate": null
    },
    {
      "date": "2000-08",
      "value": 766642,
      "sourcePeriodType": "month",
      "sourceDate": null
    },
    {
      "date": "2000-09",
      "value": 692657,
      "sourcePeriodType": "month",
      "sourceDate": null
    },
    {
      "date": "2000-10",
      "value": 653437,
      "sourcePeriodType": "month",
      "sourceDate": null
    },
    {
      "date": "2000-11",
      "value": 699230,
      "sourcePeriodType": "month",
      "sourceDate": null
    },
    {
      "date": "2000-12",
      "value": 691162,
      "sourcePeriodType": "month",
      "sourceDate": null
    },
    {
      "date": "2001-01",
      "value": 736631,
      "sourcePeriodType": "month",
      "sourceDate": null
    },
    {
      "date": "2001-02",
      "value": 716173,
      "sourcePeriodType": "month",
      "sourceDate": null
    },
    {
      "date": "2001-03",
      "value": 571553,
      "sourcePeriodType": "month",
      "sourceDate": null
    },
    {
      "date": "2001-04",
      "value": 567729,
      "sourcePeriodType": "month",
      "sourceDate": null
    },
    {
      "date": "2001-05",
      "value": 595938,
      "sourcePeriodType": "month",
      "sourceDate": null
    },
    {
      "date": "2001-06",
      "value": 553230,
      "sourcePeriodType": "month",
      "sourceDate": null
    },
    {
      "date": "2001-07",
      "value": 531576,
      "sourcePeriodType": "month",
      "sourceDate": null
    },
    {
      "date": "2001-08",
      "value": 523036,
      "sourcePeriodType": "month",
      "sourceDate": null
    },
    {
      "date": "2001-09",
      "value": 456263,
      "sourcePeriodType": "month",
      "sourceDate": null
    },
    {
      "date": "2001-10",
      "value": 481851,
      "sourcePeriodType": "month",
      "sourceDate": null
    },
    {
      "date": "2001-11",
      "value": 535723.7,
      "sourcePeriodType": "month",
      "sourceDate": null
    },
    {
      "date": "2001-12",
      "value": 532328,
      "sourcePeriodType": "month",
      "sourceDate": null
    },
    {
      "date": "2002-01",
      "value": 544397,
      "sourcePeriodType": "month",
      "sourceDate": null
    },
    {
      "date": "2002-02",
      "value": 596716.34,
      "sourcePeriodType": "month",
      "sourceDate": null
    },
    {
      "date": "2002-03",
      "value": 612224,
      "sourcePeriodType": "month",
      "sourceDate": null
    },
    {
      "date": "2002-04",
      "value": 625586.61,
      "sourcePeriodType": "month",
      "sourceDate": null
    },
    {
      "date": "2002-05",
      "value": 605065.3,
      "sourcePeriodType": "month",
      "sourceDate": null
    },
    {
      "date": "2002-06",
      "value": 637753,
      "sourcePeriodType": "month",
      "sourceDate": null
    },
    {
      "date": "2002-07",
      "value": 584041.92,
      "sourcePeriodType": "month",
      "sourceDate": null
    },
    {
      "date": "2002-08",
      "value": 605302.72,
      "sourcePeriodType": "month",
      "sourceDate": null
    },
    {
      "date": "2002-09",
      "value": 570273.49,
      "sourcePeriodType": "month",
      "sourceDate": null
    },
    {
      "date": "2002-10",
      "value": 563750.07,
      "sourcePeriodType": "month",
      "sourceDate": null
    },
    {
      "date": "2002-11",
      "value": 601289.35,
      "sourcePeriodType": "month",
      "sourceDate": null
    },
    {
      "date": "2002-12",
      "value": 628197.35,
      "sourcePeriodType": "month",
      "sourceDate": null
    },
    {
      "date": "2003-01",
      "value": 611472,
      "sourcePeriodType": "month",
      "sourceDate": null
    },
    {
      "date": "2003-02",
      "value": 619872.6,
      "sourcePeriodType": "month",
      "sourceDate": null
    },
    {
      "date": "2003-03",
      "value": 572198,
      "sourcePeriodType": "month",
      "sourceDate": null
    },
    {
      "date": "2003-04",
      "value": 572526,
      "sourcePeriodType": "month",
      "sourceDate": null
    },
    {
      "date": "2003-05",
      "value": 660982,
      "sourcePeriodType": "month",
      "sourceDate": null
    },
    {
      "date": "2003-06",
      "value": 734389,
      "sourcePeriodType": "month",
      "sourceDate": null
    },
    {
      "date": "2003-07",
      "value": 775996,
      "sourcePeriodType": "month",
      "sourceDate": null
    },
    {
      "date": "2003-08",
      "value": 905193,
      "sourcePeriodType": "month",
      "sourceDate": null
    },
    {
      "date": "2003-09",
      "value": 933087,
      "sourcePeriodType": "month",
      "sourceDate": null
    },
    {
      "date": "2003-10",
      "value": 1000494,
      "sourcePeriodType": "month",
      "sourceDate": null
    },
    {
      "date": "2003-11",
      "value": 1065853,
      "sourcePeriodType": "month",
      "sourceDate": null
    },
    {
      "date": "2003-12",
      "value": 1273361.02,
      "sourcePeriodType": "month",
      "sourceDate": null
    },
    {
      "date": "2004-01",
      "value": 1206854,
      "sourcePeriodType": "month",
      "sourceDate": null
    },
    {
      "date": "2004-02",
      "value": 1196221,
      "sourcePeriodType": "month",
      "sourceDate": null
    },
    {
      "date": "2004-03",
      "value": 1201207,
      "sourcePeriodType": "month",
      "sourceDate": null
    },
    {
      "date": "2004-04",
      "value": 1255347,
      "sourcePeriodType": "month",
      "sourceDate": null
    },
    {
      "date": "2004-05",
      "value": 1023129,
      "sourcePeriodType": "month",
      "sourceDate": null
    },
    {
      "date": "2004-06",
      "value": 1047258,
      "sourcePeriodType": "month",
      "sourceDate": null
    },
    {
      "date": "2004-07",
      "value": 1135589,
      "sourcePeriodType": "month",
      "sourceDate": null
    },
    {
      "date": "2004-08",
      "value": 1216567,
      "sourcePeriodType": "month",
      "sourceDate": null
    },
    {
      "date": "2004-09",
      "value": 1309318,
      "sourcePeriodType": "month",
      "sourceDate": null
    },
    {
      "date": "2004-10",
      "value": 1337190,
      "sourcePeriodType": "month",
      "sourceDate": null
    },
    {
      "date": "2004-11",
      "value": 1539595,
      "sourcePeriodType": "month",
      "sourceDate": null
    },
    {
      "date": "2004-12",
      "value": 1685989,
      "sourcePeriodType": "month",
      "sourceDate": null
    },
    {
      "date": "2005-01",
      "value": 1661532,
      "sourcePeriodType": "month",
      "sourceDate": null
    },
    {
      "date": "2005-02",
      "value": 1730940.44,
      "sourcePeriodType": "month",
      "sourceDate": null
    },
    {
      "date": "2005-03",
      "value": 1698428,
      "sourcePeriodType": "month",
      "sourceDate": null
    },
    {
      "date": "2005-04",
      "value": 1635766.19,
      "sourcePeriodType": "month",
      "sourceDate": null
    },
    {
      "date": "2005-05",
      "value": 1783221,
      "sourcePeriodType": "month",
      "sourceDate": null
    },
    {
      "date": "2005-06",
      "value": 1850377,
      "sourcePeriodType": "month",
      "sourceDate": null
    },
    {
      "date": "2005-07",
      "value": 1987170,
      "sourcePeriodType": "month",
      "sourceDate": null
    },
    {
      "date": "2005-08",
      "value": 2123901,
      "sourcePeriodType": "month",
      "sourceDate": null
    },
    {
      "date": "2005-09",
      "value": 2254378,
      "sourcePeriodType": "month",
      "sourceDate": null
    },
    {
      "date": "2005-10",
      "value": 2065612,
      "sourcePeriodType": "month",
      "sourceDate": null
    },
    {
      "date": "2005-11",
      "value": 2323065,
      "sourcePeriodType": "month",
      "sourceDate": null
    },
    {
      "date": "2005-12",
      "value": 2489386,
      "sourcePeriodType": "month",
      "sourceDate": null
    },
    {
      "date": "2006-01",
      "value": 2616194,
      "sourcePeriodType": "month",
      "sourceDate": null
    },
    {
      "date": "2006-02",
      "value": 2695543,
      "sourcePeriodType": "month",
      "sourceDate": null
    },
    {
      "date": "2006-03",
      "value": 3022191,
      "sourcePeriodType": "month",
      "sourceDate": null
    },
    {
      "date": "2006-04",
      "value": 3255565,
      "sourcePeriodType": "month",
      "sourceDate": null
    },
    {
      "date": "2006-05",
      "value": 2842050,
      "sourcePeriodType": "month",
      "sourceDate": null
    },
    {
      "date": "2006-06",
      "value": 2721678,
      "sourcePeriodType": "month",
      "sourceDate": null
    },
    {
      "date": "2006-07",
      "value": 2712144,
      "sourcePeriodType": "month",
      "sourceDate": null
    },
    {
      "date": "2006-08",
      "value": 2993780,
      "sourcePeriodType": "month",
      "sourceDate": null
    },
    {
      "date": "2006-09",
      "value": 3185680,
      "sourcePeriodType": "month",
      "sourceDate": null
    },
    {
      "date": "2006-10",
      "value": 3370676,
      "sourcePeriodType": "month",
      "sourceDate": null
    },
    {
      "date": "2006-11",
      "value": 3577308,
      "sourcePeriodType": "month",
      "sourceDate": null
    },
    {
      "date": "2006-12",
      "value": 3624357,
      "sourcePeriodType": "month",
      "sourceDate": null
    },
    {
      "date": "2007-01",
      "value": 3779742,
      "sourcePeriodType": "month",
      "sourceDate": null
    },
    {
      "date": "2007-02",
      "value": 3489214,
      "sourcePeriodType": "month",
      "sourceDate": null
    },
    {
      "date": "2007-03",
      "value": 3545041,
      "sourcePeriodType": "month",
      "sourceDate": null
    },
    {
      "date": "2007-04",
      "value": 3828337,
      "sourcePeriodType": "month",
      "sourceDate": null
    },
    {
      "date": "2007-05",
      "value": 4074552,
      "sourcePeriodType": "month",
      "sourceDate": null
    },
    {
      "date": "2007-06",
      "value": 4168272,
      "sourcePeriodType": "month",
      "sourceDate": null
    },
    {
      "date": "2007-07",
      "value": 4529772,
      "sourcePeriodType": "month",
      "sourceDate": null
    },
    {
      "date": "2007-08",
      "value": 4538006,
      "sourcePeriodType": "month",
      "sourceDate": null
    },
    {
      "date": "2007-09",
      "value": 5202955,
      "sourcePeriodType": "month",
      "sourceDate": null
    },
    {
      "date": "2007-10",
      "value": 6332093,
      "sourcePeriodType": "month",
      "sourceDate": null
    },
    {
      "date": "2007-11",
      "value": 6385475,
      "sourcePeriodType": "month",
      "sourceDate": null
    },
    {
      "date": "2007-12",
      "value": 7169985,
      "sourcePeriodType": "month",
      "sourceDate": null
    },
    {
      "date": "2008-01",
      "value": 5796078.8,
      "sourcePeriodType": "month",
      "sourceDate": null
    },
    {
      "date": "2008-02",
      "value": 5888447.67,
      "sourcePeriodType": "month",
      "sourceDate": null
    },
    {
      "date": "2008-03",
      "value": 5138015,
      "sourcePeriodType": "month",
      "sourceDate": null
    },
    {
      "date": "2008-04",
      "value": 5794293,
      "sourcePeriodType": "month",
      "sourceDate": null
    },
    {
      "date": "2008-05",
      "value": 5428879,
      "sourcePeriodType": "month",
      "sourceDate": null
    },
    {
      "date": "2008-06",
      "value": 4375022,
      "sourcePeriodType": "month",
      "sourceDate": null
    },
    {
      "date": "2008-07",
      "value": 4732545,
      "sourcePeriodType": "month",
      "sourceDate": null
    },
    {
      "date": "2008-08",
      "value": 4778865,
      "sourcePeriodType": "month",
      "sourceDate": null
    },
    {
      "date": "2008-09",
      "value": 4165388,
      "sourcePeriodType": "month",
      "sourceDate": null
    },
    {
      "date": "2008-10",
      "value": 2997261,
      "sourcePeriodType": "month",
      "sourceDate": null
    },
    {
      "date": "2008-11",
      "value": 2818965,
      "sourcePeriodType": "month",
      "sourceDate": null
    },
    {
      "date": "2008-12",
      "value": 3144768,
      "sourcePeriodType": "month",
      "sourceDate": null
    },
    {
      "date": "2009-01",
      "value": 2997261,
      "sourcePeriodType": "month",
      "sourceDate": null
    },
    {
      "date": "2009-02",
      "value": 2862873,
      "sourcePeriodType": "month",
      "sourceDate": null
    },
    {
      "date": "2009-03",
      "value": 3086076,
      "sourcePeriodType": "month",
      "sourceDate": null
    },
    {
      "date": "2009-04",
      "value": 3586979,
      "sourcePeriodType": "month",
      "sourceDate": null
    },
    {
      "date": "2009-05",
      "value": 4865046,
      "sourcePeriodType": "month",
      "sourceDate": null
    },
    {
      "date": "2009-06",
      "value": 4749935,
      "sourcePeriodType": "month",
      "sourceDate": null
    },
    {
      "date": "2009-07",
      "value": 5139943,
      "sourcePeriodType": "month",
      "sourceDate": null
    },
    {
      "date": "2009-08",
      "value": 5285658,
      "sourcePeriodType": "month",
      "sourceDate": null
    },
    {
      "date": "2009-09",
      "value": 5708338,
      "sourcePeriodType": "month",
      "sourceDate": null
    },
    {
      "date": "2009-10",
      "value": 5375921,
      "sourcePeriodType": "month",
      "sourceDate": null
    },
    {
      "date": "2009-11",
      "value": 5795210,
      "sourcePeriodType": "month",
      "sourceDate": null
    },
    {
      "date": "2009-12",
      "value": 6081309,
      "sourcePeriodType": "month",
      "sourceDate": null
    },
    {
      "date": "2010-01",
      "value": 5925726,
      "sourcePeriodType": "month",
      "sourceDate": null
    },
    {
      "date": "2010-02",
      "value": 5904930,
      "sourcePeriodType": "month",
      "sourceDate": null
    },
    {
      "date": "2010-03",
      "value": 6165620,
      "sourcePeriodType": "month",
      "sourceDate": null
    },
    {
      "date": "2010-04",
      "value": 6283197,
      "sourcePeriodType": "month",
      "sourceDate": null
    },
    {
      "date": "2010-05",
      "value": 6091265,
      "sourcePeriodType": "month",
      "sourceDate": null
    },
    {
      "date": "2010-06",
      "value": 6394002,
      "sourcePeriodType": "month",
      "sourceDate": null
    },
    {
      "date": "2010-07",
      "value": 6510778,
      "sourcePeriodType": "month",
      "sourceDate": null
    },
    {
      "date": "2010-08",
      "value": 6562026,
      "sourcePeriodType": "month",
      "sourceDate": null
    },
    {
      "date": "2010-09",
      "value": 7125807,
      "sourcePeriodType": "month",
      "sourceDate": null
    },
    {
      "date": "2010-10",
      "value": 7224908,
      "sourcePeriodType": "month",
      "sourceDate": null
    },
    {
      "date": "2010-11",
      "value": 7067845,
      "sourcePeriodType": "month",
      "sourceDate": null
    },
    {
      "date": "2010-12",
      "value": 7296726,
      "sourcePeriodType": "month",
      "sourceDate": null
    },
    {
      "date": "2011-01",
      "value": 6595279,
      "sourcePeriodType": "month",
      "sourceDate": null
    },
    {
      "date": "2011-02",
      "value": 6343073,
      "sourcePeriodType": "month",
      "sourceDate": null
    },
    {
      "date": "2011-03",
      "value": 6839084,
      "sourcePeriodType": "month",
      "sourceDate": null
    },
    {
      "date": "2011-04",
      "value": 6908090,
      "sourcePeriodType": "month",
      "sourceDate": null
    },
    {
      "date": "2011-05",
      "value": 6731869,
      "sourcePeriodType": "month",
      "sourceDate": null
    },
    {
      "date": "2011-06",
      "value": 6730947,
      "sourcePeriodType": "month",
      "sourceDate": null
    },
    {
      "date": "2011-07",
      "value": 6617273,
      "sourcePeriodType": "month",
      "sourceDate": null
    },
    {
      "date": "2011-08",
      "value": 6061626,
      "sourcePeriodType": "month",
      "sourceDate": null
    },
    {
      "date": "2011-09",
      "value": 5955167,
      "sourcePeriodType": "month",
      "sourceDate": null
    },
    {
      "date": "2011-10",
      "value": 6240155,
      "sourcePeriodType": "month",
      "sourceDate": null
    },
    {
      "date": "2011-11",
      "value": 5672255,
      "sourcePeriodType": "month",
      "sourceDate": null
    },
    {
      "date": "2011-12",
      "value": 5348645,
      "sourcePeriodType": "month",
      "sourceDate": null
    },
    {
      "date": "2012-01",
      "value": 6059347,
      "sourcePeriodType": "month",
      "sourceDate": null
    },
    {
      "date": "2012-02",
      "value": 6356697,
      "sourcePeriodType": "month",
      "sourceDate": null
    },
    {
      "date": "2012-03",
      "value": 6214912,
      "sourcePeriodType": "month",
      "sourceDate": null
    },
    {
      "date": "2012-04",
      "value": 6177685,
      "sourcePeriodType": "month",
      "sourceDate": null
    },
    {
      "date": "2012-05",
      "value": 5817422,
      "sourcePeriodType": "month",
      "sourceDate": null
    },
    {
      "date": "2012-06",
      "value": 6155647,
      "sourcePeriodType": "month",
      "sourceDate": null
    },
    {
      "date": "2012-07",
      "value": 6081389,
      "sourcePeriodType": "month",
      "sourceDate": null
    },
    {
      "date": "2012-08",
      "value": 6080798,
      "sourcePeriodType": "month",
      "sourceDate": null
    },
    {
      "date": "2012-09",
      "value": 6559050,
      "sourcePeriodType": "month",
      "sourceDate": null
    },
    {
      "date": "2012-10",
      "value": 6471051,
      "sourcePeriodType": "month",
      "sourceDate": null
    },
    {
      "date": "2012-11",
      "value": 6738713,
      "sourcePeriodType": "month",
      "sourceDate": null
    },
    {
      "date": "2012-12",
      "value": 6921815,
      "sourcePeriodType": "month",
      "sourceDate": null
    },
    {
      "date": "2013-01",
      "value": 7024577,
      "sourcePeriodType": "month",
      "sourceDate": null
    },
    {
      "date": "2013-02",
      "value": 6538038,
      "sourcePeriodType": "month",
      "sourceDate": null
    },
    {
      "date": "2013-03",
      "value": 6387887,
      "sourcePeriodType": "month",
      "sourceDate": null
    },
    {
      "date": "2013-04",
      "value": 6645785,
      "sourcePeriodType": "month",
      "sourceDate": null
    },
    {
      "date": "2013-05",
      "value": 6679134,
      "sourcePeriodType": "month",
      "sourceDate": null
    },
    {
      "date": "2013-06",
      "value": 6405118,
      "sourcePeriodType": "month",
      "sourceDate": null
    },
    {
      "date": "2013-07",
      "value": 6263106,
      "sourcePeriodType": "month",
      "sourceDate": null
    },
    {
      "date": "2013-08",
      "value": 6030078,
      "sourcePeriodType": "month",
      "sourceDate": null
    },
    {
      "date": "2013-09",
      "value": 6386134,
      "sourcePeriodType": "month",
      "sourceDate": null
    },
    {
      "date": "2013-10",
      "value": 6844233,
      "sourcePeriodType": "month",
      "sourceDate": null
    },
    {
      "date": "2013-11",
      "value": 6810475,
      "sourcePeriodType": "month",
      "sourceDate": null
    },
    {
      "date": "2013-12",
      "value": 7044258,
      "sourcePeriodType": "month",
      "sourceDate": null
    },
    {
      "date": "2014-01",
      "value": 6744398,
      "sourcePeriodType": "month",
      "sourceDate": null
    },
    {
      "date": "2014-02",
      "value": 6893083,
      "sourcePeriodType": "month",
      "sourceDate": null
    },
    {
      "date": "2014-03",
      "value": 7415296,
      "sourcePeriodType": "month",
      "sourceDate": null
    },
    {
      "date": "2014-04",
      "value": 7494791,
      "sourcePeriodType": "month",
      "sourceDate": null
    },
    {
      "date": "2014-05",
      "value": 8407834,
      "sourcePeriodType": "month",
      "sourceDate": null
    },
    {
      "date": "2014-06",
      "value": 9020000,
      "sourcePeriodType": "month",
      "sourceDate": null
    },
    {
      "date": "2014-07",
      "value": 9010270,
      "sourcePeriodType": "month",
      "sourceDate": null
    },
    {
      "date": "2014-08",
      "value": 9259481,
      "sourcePeriodType": "month",
      "sourceDate": null
    },
    {
      "date": "2014-09",
      "value": 9382249,
      "sourcePeriodType": "month",
      "sourceDate": null
    },
    {
      "date": "2014-10",
      "value": 9684691,
      "sourcePeriodType": "month",
      "sourceDate": null
    },
    {
      "date": "2014-11",
      "value": 9982564,
      "sourcePeriodType": "month",
      "sourceDate": null
    },
    {
      "date": "2014-12",
      "value": 9836377,
      "sourcePeriodType": "month",
      "sourceDate": null
    },
    {
      "date": "2015-01",
      "value": 10346282,
      "sourcePeriodType": "month",
      "sourceDate": null
    },
    {
      "date": "2015-02",
      "value": 10466661,
      "sourcePeriodType": "month",
      "sourceDate": null
    },
    {
      "date": "2015-03",
      "value": 10149290,
      "sourcePeriodType": "month",
      "sourceDate": null
    },
    {
      "date": "2015-04",
      "value": 9968015,
      "sourcePeriodType": "month",
      "sourceDate": null
    },
    {
      "date": "2015-05",
      "value": 10326686,
      "sourcePeriodType": "month",
      "sourceDate": null
    },
    {
      "date": "2015-06",
      "value": 10143511,
      "sourcePeriodType": "month",
      "sourceDate": null
    },
    {
      "date": "2015-07",
      "value": 10479396,
      "sourcePeriodType": "month",
      "sourceDate": null
    },
    {
      "date": "2015-08",
      "value": 9827930,
      "sourcePeriodType": "month",
      "sourceDate": null
    },
    {
      "date": "2015-09",
      "value": 9648122,
      "sourcePeriodType": "month",
      "sourceDate": null
    },
    {
      "date": "2015-10",
      "value": 9833359,
      "sourcePeriodType": "month",
      "sourceDate": null
    },
    {
      "date": "2015-11",
      "value": 9888227,
      "sourcePeriodType": "month",
      "sourceDate": null
    },
    {
      "date": "2015-12",
      "value": 10037734,
      "sourcePeriodType": "month",
      "sourceDate": null
    },
    {
      "date": "2016-01",
      "value": 9392133,
      "sourcePeriodType": "month",
      "sourceDate": null
    },
    {
      "date": "2016-02",
      "value": 8583145,
      "sourcePeriodType": "month",
      "sourceDate": null
    },
    {
      "date": "2016-03",
      "value": 9475328,
      "sourcePeriodType": "month",
      "sourceDate": null
    },
    {
      "date": "2016-04",
      "value": 9710539,
      "sourcePeriodType": "month",
      "sourceDate": null
    },
    {
      "date": "2016-05",
      "value": 9928678,
      "sourcePeriodType": "month",
      "sourceDate": null
    },
    {
      "date": "2016-06",
      "value": 10285549,
      "sourcePeriodType": "month",
      "sourceDate": null
    },
    {
      "date": "2016-07",
      "value": 10863580,
      "sourcePeriodType": "month",
      "sourceDate": null
    },
    {
      "date": "2016-08",
      "value": 11099423,
      "sourcePeriodType": "month",
      "sourceDate": null
    },
    {
      "date": "2016-09",
      "value": 11073648,
      "sourcePeriodType": "month",
      "sourceDate": null
    },
    {
      "date": "2016-10",
      "value": 11406693,
      "sourcePeriodType": "month",
      "sourceDate": null
    },
    {
      "date": "2016-11",
      "value": 10788709,
      "sourcePeriodType": "month",
      "sourceDate": null
    },
    {
      "date": "2016-12",
      "value": 10623347,
      "sourcePeriodType": "month",
      "sourceDate": null
    },
    {
      "date": "2017-01",
      "value": 11256330,
      "sourcePeriodType": "month",
      "sourceDate": null
    },
    {
      "date": "2017-02",
      "value": 11759367,
      "sourcePeriodType": "month",
      "sourceDate": null
    },
    {
      "date": "2017-03",
      "value": 12154525,
      "sourcePeriodType": "month",
      "sourceDate": null
    },
    {
      "date": "2017-04",
      "value": 12484975,
      "sourcePeriodType": "month",
      "sourceDate": null
    },
    {
      "date": "2017-05",
      "value": 12580119,
      "sourcePeriodType": "month",
      "sourceDate": null
    },
    {
      "date": "2017-06",
      "value": 12596812,
      "sourcePeriodType": "month",
      "sourceDate": null
    },
    {
      "date": "2017-07",
      "value": 13262246,
      "sourcePeriodType": "month",
      "sourceDate": null
    },
    {
      "date": "2017-08",
      "value": 13189762.82,
      "sourcePeriodType": "month",
      "sourceDate": null
    },
    {
      "date": "2017-09",
      "value": 13181353.14,
      "sourcePeriodType": "month",
      "sourceDate": null
    },
    {
      "date": "2017-10",
      "value": 14391546,
      "sourcePeriodType": "month",
      "sourceDate": null
    },
    {
      "date": "2017-11",
      "value": 14596655.54,
      "sourcePeriodType": "month",
      "sourceDate": null
    },
    {
      "date": "2017-12",
      "value": 15173866.88,
      "sourcePeriodType": "month",
      "sourceDate": null
    },
    {
      "date": "2018-01",
      "value": 15320977.74,
      "sourcePeriodType": "month",
      "sourceDate": null
    },
    {
      "date": "2018-02",
      "value": 14765583.17,
      "sourcePeriodType": "month",
      "sourceDate": null
    },
    {
      "date": "2018-03",
      "value": 14224996.97,
      "sourcePeriodType": "month",
      "sourceDate": null
    },
    {
      "date": "2018-04",
      "value": 15279535,
      "sourcePeriodType": "month",
      "sourceDate": null
    },
    {
      "date": "2018-05",
      "value": 14869671.1,
      "sourcePeriodType": "month",
      "sourceDate": null
    },
    {
      "date": "2018-06",
      "value": 14501942,
      "sourcePeriodType": "month",
      "sourceDate": null
    },
    {
      "date": "2018-07",
      "value": 15314574.3,
      "sourcePeriodType": "month",
      "sourceDate": null
    },
    {
      "date": "2018-08",
      "value": 15934696,
      "sourcePeriodType": "month",
      "sourceDate": null
    },
    {
      "date": "2018-09",
      "value": 14486402,
      "sourcePeriodType": "month",
      "sourceDate": null
    },
    {
      "date": "2018-10",
      "value": 13845109,
      "sourcePeriodType": "month",
      "sourceDate": null
    },
    {
      "date": "2018-11",
      "value": 14288775.86,
      "sourcePeriodType": "month",
      "sourceDate": null
    },
    {
      "date": "2018-12",
      "value": 14448465.69,
      "sourcePeriodType": "month",
      "sourceDate": null
    },
    {
      "date": "2019-01",
      "value": 14099330.09,
      "sourcePeriodType": "month",
      "sourceDate": null
    },
    {
      "date": "2019-02",
      "value": 14041530.33,
      "sourcePeriodType": "month",
      "sourceDate": null
    },
    {
      "date": "2019-03",
      "value": 15108711,
      "sourcePeriodType": "month",
      "sourceDate": null
    },
    {
      "date": "2019-04",
      "value": 15254028.06,
      "sourcePeriodType": "month",
      "sourceDate": null
    },
    {
      "date": "2019-05",
      "value": 15438014.55,
      "sourcePeriodType": "month",
      "sourceDate": null
    },
    {
      "date": "2019-06",
      "value": 15197087.37,
      "sourcePeriodType": "month",
      "sourceDate": null
    },
    {
      "date": "2019-07",
      "value": 14147124.63,
      "sourcePeriodType": "month",
      "sourceDate": null
    },
    {
      "date": "2019-08",
      "value": 14098452,
      "sourcePeriodType": "month",
      "sourceDate": null
    },
    {
      "date": "2019-09",
      "value": 14717456.1,
      "sourcePeriodType": "month",
      "sourceDate": null
    },
    {
      "date": "2019-10",
      "value": 15409067.51,
      "sourcePeriodType": "month",
      "sourceDate": null
    },
    {
      "date": "2019-11",
      "value": 15475077.14,
      "sourcePeriodType": "month",
      "sourceDate": null
    },
    {
      "date": "2019-12",
      "value": 15553829,
      "sourcePeriodType": "month",
      "sourceDate": null
    },
    {
      "date": "2020-01",
      "value": 15650982,
      "sourcePeriodType": "month",
      "sourceDate": null
    },
    {
      "date": "2020-02",
      "value": 14687010.42,
      "sourcePeriodType": "month",
      "sourceDate": null
    },
    {
      "date": "2020-03",
      "value": 11348757,
      "sourcePeriodType": "month",
      "sourceDate": null
    },
    {
      "date": "2020-04",
      "value": 12941620.82,
      "sourcePeriodType": "month",
      "sourceDate": null
    },
    {
      "date": "2020-05",
      "value": 12706528.94,
      "sourcePeriodType": "month",
      "sourceDate": null
    },
    {
      "date": "2020-06",
      "value": 13915689.83,
      "sourcePeriodType": "month",
      "sourceDate": null
    },
    {
      "date": "2020-07",
      "value": 14739115.83,
      "sourcePeriodType": "month",
      "sourceDate": null
    },
    {
      "date": "2020-08",
      "value": 15376302.71,
      "sourcePeriodType": "month",
      "sourceDate": null
    },
    {
      "date": "2020-09",
      "value": 15524267.37,
      "sourcePeriodType": "month",
      "sourceDate": null
    },
    {
      "date": "2020-10",
      "value": 15792249.91,
      "sourcePeriodType": "month",
      "sourceDate": null
    },
    {
      "date": "2020-11",
      "value": 17414859.59,
      "sourcePeriodType": "month",
      "sourceDate": null
    },
    {
      "date": "2020-12",
      "value": 18803518.6,
      "sourcePeriodType": "month",
      "sourceDate": null
    },
    {
      "date": "2021-01",
      "value": 18612644.03,
      "sourcePeriodType": "month",
      "sourceDate": null
    },
    {
      "date": "2021-02",
      "value": 20081095.73,
      "sourcePeriodType": "month",
      "sourceDate": null
    },
    {
      "date": "2021-03",
      "value": 20430814.54,
      "sourcePeriodType": "month",
      "sourceDate": null
    },
    {
      "date": "2021-04",
      "value": 20702706.49,
      "sourcePeriodType": "month",
      "sourceDate": null
    },
    {
      "date": "2021-05",
      "value": 22299810.27,
      "sourcePeriodType": "month",
      "sourceDate": null
    },
    {
      "date": "2021-06",
      "value": 22977769,
      "sourcePeriodType": "month",
      "sourceDate": null
    },
    {
      "date": "2021-07",
      "value": 23549749,
      "sourcePeriodType": "month",
      "sourceDate": null
    },
    {
      "date": "2021-08",
      "value": 25002084,
      "sourcePeriodType": "month",
      "sourceDate": null
    },
    {
      "date": "2021-09",
      "value": 25986747,
      "sourcePeriodType": "month",
      "sourceDate": null
    },
    {
      "date": "2021-10",
      "value": 25920458.07,
      "sourcePeriodType": "month",
      "sourceDate": null
    },
    {
      "date": "2021-11",
      "value": 25717228.45,
      "sourcePeriodType": "month",
      "sourceDate": null
    },
    {
      "date": "2021-12",
      "value": 26600211.55,
      "sourcePeriodType": "month",
      "sourceDate": null
    },
    {
      "date": "2022-01",
      "value": 26441207.18,
      "sourcePeriodType": "month",
      "sourceDate": null
    },
    {
      "date": "2022-02",
      "value": 25239045.09,
      "sourcePeriodType": "month",
      "sourceDate": null
    },
    {
      "date": "2022-03",
      "value": 26406501.38,
      "sourcePeriodType": "month",
      "sourceDate": null
    },
    {
      "date": "2022-04",
      "value": 26697882.22,
      "sourcePeriodType": "month",
      "sourceDate": null
    },
    {
      "date": "2022-05",
      "value": 25778368.28,
      "sourcePeriodType": "month",
      "sourceDate": null
    },
    {
      "date": "2022-06",
      "value": 24373732.88,
      "sourcePeriodType": "month",
      "sourceDate": null
    },
    {
      "date": "2022-07",
      "value": 26658604.02,
      "sourcePeriodType": "month",
      "sourceDate": null
    },
    {
      "date": "2022-08",
      "value": 28024621.83,
      "sourcePeriodType": "month",
      "sourceDate": null
    },
    {
      "date": "2022-09",
      "value": 27184601.83,
      "sourcePeriodType": "month",
      "sourceDate": null
    },
    {
      "date": "2022-10",
      "value": 27991936.92,
      "sourcePeriodType": "month",
      "sourceDate": null
    },
    {
      "date": "2022-11",
      "value": 28850896.03,
      "sourcePeriodType": "month",
      "sourceDate": null
    },
    {
      "date": "2022-12",
      "value": 28238247.93,
      "sourcePeriodType": "month",
      "sourceDate": null
    },
    {
      "date": "2023-01",
      "value": 27023159.98,
      "sourcePeriodType": "month",
      "sourceDate": null
    },
    {
      "date": "2023-02",
      "value": 25772501.4,
      "sourcePeriodType": "month",
      "sourceDate": null
    },
    {
      "date": "2023-03",
      "value": 25819896,
      "sourcePeriodType": "month",
      "sourceDate": null
    },
    {
      "date": "2023-04",
      "value": 27182858.92,
      "sourcePeriodType": "month",
      "sourceDate": null
    },
    {
      "date": "2023-05",
      "value": 28376277.78,
      "sourcePeriodType": "month",
      "sourceDate": null
    },
    {
      "date": "2023-06",
      "value": 29648153.59,
      "sourcePeriodType": "month",
      "sourceDate": null
    },
    {
      "date": "2023-07",
      "value": 30666348.99,
      "sourcePeriodType": "month",
      "sourceDate": null
    },
    {
      "date": "2023-08",
      "value": 30959138.7,
      "sourcePeriodType": "month",
      "sourceDate": null
    },
    {
      "date": "2023-09",
      "value": 31906871.94,
      "sourcePeriodType": "month",
      "sourceDate": null
    },
    {
      "date": "2023-10",
      "value": 31145025.49,
      "sourcePeriodType": "month",
      "sourceDate": null
    },
    {
      "date": "2023-11",
      "value": 33560155.58,
      "sourcePeriodType": "month",
      "sourceDate": null
    },
    {
      "date": "2023-12",
      "value": 36428846.25,
      "sourcePeriodType": "month",
      "sourceDate": null
    },
    {
      "date": "2024-01",
      "value": 37978375.88,
      "sourcePeriodType": "month",
      "sourceDate": null
    },
    {
      "date": "2024-02",
      "value": 38795690.23,
      "sourcePeriodType": "month",
      "sourceDate": null
    },
    {
      "date": "2024-03",
      "value": 38697099.77,
      "sourcePeriodType": "month",
      "sourceDate": null
    },
    {
      "date": "2024-04",
      "value": 40655851.94,
      "sourcePeriodType": "month",
      "sourceDate": null
    },
    {
      "date": "2024-05",
      "value": 41212881.14,
      "sourcePeriodType": "month",
      "sourceDate": null
    },
    {
      "date": "2024-06",
      "value": 43924743.63,
      "sourcePeriodType": "month",
      "sourceDate": null
    },
    {
      "date": "2024-07",
      "value": 46238008.35,
      "sourcePeriodType": "month",
      "sourceDate": null
    },
    {
      "date": "2024-08",
      "value": 46439993.77,
      "sourcePeriodType": "month",
      "sourceDate": null
    },
    {
      "date": "2024-09",
      "value": 47435137.15,
      "sourcePeriodType": "month",
      "sourceDate": null
    },
    {
      "date": "2024-10",
      "value": 44471429.92,
      "sourcePeriodType": "month",
      "sourceDate": null
    },
    {
      "date": "2024-11",
      "value": 44668650.36,
      "sourcePeriodType": "month",
      "sourceDate": null
    },
    {
      "date": "2024-12",
      "value": 44195106.44,
      "sourcePeriodType": "month",
      "sourceDate": null
    },
    {
      "date": "2025-01",
      "value": 42402091.54,
      "sourcePeriodType": "month",
      "sourceDate": null
    },
    {
      "date": "2025-02",
      "value": 38401411.86,
      "sourcePeriodType": "month",
      "sourceDate": null
    },
    {
      "date": "2025-03",
      "value": 41287646.5,
      "sourcePeriodType": "month",
      "sourceDate": null
    },
    {
      "date": "2025-04",
      "value": 42324763.25,
      "sourcePeriodType": "month",
      "sourceDate": null
    },
    {
      "date": "2025-05",
      "value": 44419342.02,
      "sourcePeriodType": "month",
      "sourceDate": null
    },
    {
      "date": "2025-06",
      "value": 46116672.35,
      "sourcePeriodType": "month",
      "sourceDate": null
    },
    {
      "date": "2025-07",
      "value": 44972018.75,
      "sourcePeriodType": "month",
      "sourceDate": null
    },
    {
      "date": "2025-08",
      "value": 44365504.09,
      "sourcePeriodType": "month",
      "sourceDate": null
    },
    {
      "date": "2025-09",
      "value": 45144414.11,
      "sourcePeriodType": "month",
      "sourceDate": null
    },
    {
      "date": "2025-10",
      "value": 47026401.4,
      "sourcePeriodType": "month",
      "sourceDate": null
    },
    {
      "date": "2025-11",
      "value": 47435859.94,
      "sourcePeriodType": "month",
      "sourceDate": null
    },
    {
      "date": "2025-12",
      "value": 47579238.11,
      "sourcePeriodType": "month",
      "sourceDate": null
    },
    {
      "date": "2026-01",
      "value": 46002240.35,
      "sourcePeriodType": "month",
      "sourceDate": null
    },
    {
      "date": "2026-02",
      "value": 46350671.27,
      "sourcePeriodType": "month",
      "sourceDate": null
    },
    {
      "date": "2026-03",
      "value": 41241172.45,
      "sourcePeriodType": "month",
      "sourceDate": null
    },
    {
      "date": "2026-04",
      "value": 46329334.1,
      "sourcePeriodType": "month",
      "sourceDate": null
    }
  ],
  "metadata": {
    "derivedFrom": "data/series/rbi-dbie.IN.macro_other_timeseries.long.json",
    "derivedFromHash": "b70d70f2c3dc44290257060792d966e9031af81ca56f5fa61b48b8a3a4836f49",
    "parentIndicatorId": "macro.rbi.dbie_other_timeseries",
    "sourceDatasetKey": "rbi_macro_other_timeseries",
    "sourceFrequency": "Monthly",
    "sourceIndicatorLabel": "MARKET CAPITALISATION - BSE",
    "sourceUnit": "₹ Crore",
    "qualityGates": [
      "exact source label/frequency/unit match",
      "finite numeric values only",
      "unique period keys",
      "minimum observation count"
    ]
  }
}
